Workbook

Sheet Start Here
A1: AI / ML & AI AGENT ENGINEERING MASTER TRACKER
A2: Evidence-Based Learning Management System & Roadmap for Building Autonomous AI Sales Employees & Commercial Products
A4: 1. LEARNER PROFILE & STRATEGIC CAREER OBJECTIVES
A5: Current OS & Tools | B5: Ubuntu Linux | VS Code | Git & GitHub | Python 3.10+ | PyTorch | FastAPI | PostgreSQL | Docker
A6: Current Background | B6: Backend development experience (Python, Django, REST APIs, SQL databases). Strong foundation in web and data services.
A7: Primary Career Goal | B7: Master AI, Machine Learning, Deep Learning, LLMs, and AI Agent Engineering from foundations to advanced commercial systems.
A8: Target Commercial Goal | B8: Design, build, deploy, and sell an Autonomous AI Sales Employee capable of performing end-to-end B2B sales cycles.
A9: Recommended Pace | B9: 12 Months | 2–3 hours per day | 6 days per week | Minimum 750–900 cumulative focused learning hours.
A11: 2. TARGET COMMERCIAL PRODUCT: AUTONOMOUS AI SALES EMPLOYEE (12 CORE CAPABILITIES)
A12: 1. Lead Discovery | B12: Automatically search web, directories, and business APIs to find relevant target customer profiles and accounts. | D12: 2. Lead Qualification | E12: Conduct background research on companies, scrape key decision-makers, and score leads using the BANT framework.
A13: 3. Needs Discovery | B13: Engage leads in consultative dialogue to identify operational pain points, budget constraints, and purchase intent. | D13: 4. Omnichannel Outreach | E13: Communicate fluently across Email (SMTP/IMAP), Web Chat, WhatsApp Business API, and Voice synthesis.
A14: 5. Product Q&A | B14: Answer complex technical and commercial questions with high accuracy using grounded Enterprise RAG pipelines. | D14: 6. Recommendation Engine | E14: Analyze lead requirements and recommend the optimal tier, product package, and customization options.
A15: 7. Guardrailed Negotiation | B15: Negotiate pricing, payment terms, and discounts strictly within predefined rule-based business boundaries. | D15: 8. Persistent Follow-ups | E15: Execute multi-touch follow-up sequences across days/weeks, adapting messaging dynamically to lead engagement.
A16: 9. Quotation & Order Generation | B16: Generate formal PDF sales quotes, proforma invoices, and capture digital signatures or checkout triggers. | D16: 10. CRM & ERP Sync | E16: Update HubSpot/Salesforce, trigger ERP workflows, write conversation logs, and synchronize pipeline status in real time.
A17: 11. Sales Analytics & Tracking | B17: Log all interaction transcripts, sentiment trends, objection patterns, and conversion rates to a central database. | D17: 12. Human Escalation (HITL) | E17: Detect sensitive negotiations, angry customers, or complex custom requests and smoothly hand off to a human manager.
A19: 3. RECOMMENDED DAILY STUDY ROUTINE (2.5 - 3.0 HOURS STRUCTURE)
A20: Step 1 (45 mins) | B20: Concept Study & Foundations | C20: Read official documentation, research papers, or mathematical foundations. Write notes in your own words.
A21: Step 2 (60 mins) | B21: Hands-On Coding & Exercises | C21: Implement algorithms from scratch (NumPy/PyTorch) or solve practical coding challenges without copying solutions.
A22: Step 3 (60 mins) | B22: Practical Project Implementation | C22: Build components for your AI Sales Employee (RAG pipeline, tool calling, FastAPI endpoints, agent state machine).
A23: Step 4 (15 mins) | B23: Review, Assessment & Logging | C23: Log actual time, update tracker, record difficulties, evaluate recall without looking at notes, and schedule revisions.
A25: 4. HOW TO USE THIS WORKBOOK (WORKSHEET NAVIGATION MAP)
A26: 1. Start Here | B26: Executive orientation, career objectives, commercial agent vision, study habits, and workbook instructions. | F26: Read once & reference monthly
A27: 2. Master Roadmap | B27: The 12-month, 12-phase curriculum from Python/math to advanced autonomous AI sales agents. | F27: Review weekly for pacing
A28: 3. Detailed Learning Tracker | B28: Primary operational log for every study session: timestamps, planned vs actual hours, confidence, evidence. | F28: Update daily after each session
A29: 4. Official Learning Resources | B29: Curated official documentation and courses from Google, OpenAI, Meta, PyTorch, Hugging Face, etc. | F29: Consult before starting topics
A30: 5. Topic Completion Checklist | B30: Granular checklist of core skills across Python, ML, DL, LLMs, Agents, Production, and Business. | F30: Update upon topic mastery
A31: 6. Tutorial & Course Tracker | B31: Monitor courses, research papers, and technical tutorials with practical exercise verification. | F31: Update as courses progress
A32: 7. AI Project Backlog | B32: The 10 foundational to enterprise-grade AI projects, culminating in the production AI sales employee. | F32: Track sprint deliverables
A33: 8. Daily Study Agenda | B33: Structured 30-day agenda breaking learning into specific, time-blocked daily deliverables. | F33: Follow daily for discipline
A34: 9. Weekly Review & Analysis | B34: Weekly honest retrospectives: planned vs actual hours, blockers, inefficiencies, and schedule adjustments. | F34: Complete every Sunday
A35: 10. Progress Dashboard | B35: Automated analytics: KPI metric cards, completion percentages, hours by phase, and dynamic charts. | F35: Review anytime for motivation
A36: 11. Notes & Document Library | B36: Repository of architecture decisions, code templates, system prompts, and research summaries. | F36: Update with key technical learnings
A37: 12. AI Experiment Log | B37: Scientific log for prompts, hyperparameters, latency benchmarks, tool accuracy, and failure cases. | F37: Log every agent/model test
A38: 13. Commercial Product Validation | B38: Customer problem validation, interview notes, willingness to pay, unit economics, and pilot metrics. | F38: Update during business validation
A40: 5. RIGOROUS COMPLETION & MASTERY VERIFICATION RULES
A41: Rule 1: Evidence Over Emotion | B41: Spending 50 hours studying or feeling confident does NOT equal mastery. Only mark 'Completed' or 'Mastered' when backed by independent code or working projects.
A42: Rule 2: Unaided Recall Test | B42: Before completing a topic, explain the core concepts in plain English without looking at any notes, tutorials, or AI chat assistants.
A43: Rule 3: Scratch Implementation | B43: Write a clean implementation from scratch. If studying Linear Regression, code the gradient descent loop. If studying Agents, write the ReAct loop without a library.
A44: Rule 4: Delayed Retention Verification | B44: Re-test yourself after 7 and 14 days. If you cannot explain or implement the concept after a week, downgrade the topic status to 'Needs Revision'.
A45: Rule 5: No Passive Tutorial Hell | B45: Never watch a video or read a tutorial passively without producing working code, test cases, or an architectural diagram committed to GitHub.

Sheet Master Roadmap
A1: 12-MONTH AI & AI AGENT ENGINEERING MASTER ROADMAP
A2: Structured 12-Phase Pathway from Foundational Mathematics & Python to Commercial Autonomous AI Employees
A4: Phase # | B4: Phase Name | C4: Learning Objectives | D4: Individual Topics | E4: Required Prerequisites | F4: Target Start Date | G4: Target Completion Date | H4: Estimated Study Hours | I4: Actual Hours | J4: Practical Exercises | K4: Expected Deliverables | L4: Success Criteria | M4: Recommended Resources | N4: Current Status | O4: Actual Completion Date | P4: Notes and Blockers
A5: 1 | B5: Python & Mathematics Foundations | C5: Establish rock-solid programming discipline and mathematical intuitions for machine learning algorithms. | D5: Python data structures, OOP, Exceptions, Typing, JSON/APIs, File I/O, Git/GitHub, Linux CLI, Linear Algebra (Vectors, Matrices, Dot Products), Probability & Statistics, Derivatives & Gradient Descent. | E5: Basic computer literacy, terminal comfort | F5: 2026-11-01 | G5: 2026-11-30 | H5: 60 | I5: 0 | J5: 1. Implement matrix multiplication from scratch without NumPy. 2. Write gradient descent optimization for 2D function. 3. Build CLI tool with API fetching and JSON caching. | K5: GitHub repo with clean Python utilities, math scratch notebooks, unit tests with pytest. | L5: Pass self-assessment test: explain eigenvalues, dot products, and write OOP Python classes with type hints and tests without reference. | M5: Python Docs, 3Blue1Brown Essense of Linear Algebra, Khan Academy Statistics | N5: Not Started
A6: 2 | B6: Data Analysis & Traditional Machine Learning | C6: Master data preprocessing, feature engineering, and classical machine learning algorithms with scikit-learn. | D6: NumPy array operations, Pandas DataFrames, Data Cleaning, Exploratory Data Analysis (EDA), Matplotlib/Seaborn, Supervised Learning (Linear/Logistic Regression, Decision Trees, Random Forests, XGBoost), Unsupervised Learning (K-Means, PCA), Overfitting, Cross-validation, Precision/Recall/F1, Data Leakage. | E6: Phase 1: Python, Linear Algebra, Statistics | F6: 2026-12-01 | G6: 2026-12-31 | H6: 75 | I6: 0 | J6: 1. Customer churn prediction with XGBoost. 2. B2B Sales transaction exploratory data analysis. 3. Implement Logistic Regression from scratch. | K6: Project 1: Sales Data Analysis & Project 2: Customer Purchase Prediction Model with full EDA notebook and metrics report. | L6: Achieve F1 > 0.82 on test split; demonstrate understanding of bias-variance tradeoff and confusion matrix. | M6: Google ML Crash Course, scikit-learn User Guide, Pandas official docs | N6: Not Started
A7: 3 | B7: Deep Learning & Neural Networks | C7: Build intuition for neural network architectures, backpropagation, and tensor computing with PyTorch. | D7: Tensors, Autograd, Multi-Layer Perceptrons (MLP), Activation Functions (ReLU, GELU, Softmax), Loss Functions (MSE, Cross-Entropy), Optimizers (SGD, AdamW), PyTorch Dataset/DataLoader, Regularization (Dropout, Weight Decay), Convolutional & Sequence Networks, Embeddings. | E7: Phase 2: NumPy, Calculus, ML concepts | F7: 2027-01-01 | G7: 2027-01-31 | H7: 80 | I7: 0 | J7: 1. Build micrograd / mini autograd engine in Python. 2. Train PyTorch neural network for customer intent classification. 3. Implement custom PyTorch Dataset for tabular/text data. | K7: Project 3: Customer Message Intent Classification model trained and evaluated in PyTorch. | L7: Explain backpropagation forward/backward pass mathematics on whiteboard; train stable PyTorch model without overfitting. | M7: PyTorch Official Tutorials, fast.ai Practical Deep Learning, Andrej Karpathy nn-zero-to-hero | N7: Not Started
A8: 4 | B8: LLM Fundamentals & Transformer Architecture | C8: Understand how Large Language Models work internally from tokenization to attention mechanisms. | D8: Tokenization (BPE, WordPiece, tiktoken), Transformer Architecture (Encoder, Decoder, Encoder-Decoder), Scaled Dot-Product Attention, Multi-Head Attention, Positional Encodings, Pretraining Objectives, Causal Masking, Context Windows, KV Caching, Quantization (GGUF, AWQ, bitsandbytes). | E8: Phase 3: PyTorch, Neural networks, Embeddings | F8: 2027-02-01 | G8: 2027-02-28 | H8: 70 | I8: 0 | J8: 1. Build self-attention and multi-head attention module in PyTorch. 2. Tokenize text using tiktoken and examine token distributions. 3. Run local quantized Llama-3 model using llama.cpp / Ollama. | K8: Clean PyTorch notebook with annotated Transformer attention layer and local inference benchmark script. | L8: Explain scaled dot-product attention equation QK^T / sqrt(d_k) and KV caching latency trade-offs without consulting notes. | M8: Attention Is All You Need paper, Hugging Face NLP Course, Jay Alammar The Illustrated Transformer | N8: Not Started
A9: 5 | B9: Prompt Engineering & LLM App Development | C9: Master programmatic interactions with state-of-the-art LLMs using official APIs, structured outputs, and evaluation. | D9: System Prompts, In-Context Learning, Few-shot prompting, Chain-of-Thought (CoT), Structured Outputs (JSON Schema / Pydantic validation), OpenAI & Gemini APIs, Error handling & retries, Token management & Cost optimization, Prompt injection defenses. | E9: Phase 1 (Python APIs) & Phase 4 (LLM basics) | F9: 2027-03-01 | G9: 2027-03-25 | H9: 55 | I9: 0 | J9: 1. Build B2B lead enrichment pipeline extracting structured JSON from raw company websites. 2. Implement robust retry with exponential backoff for rate limits. 3. Benchmark prompt variants across 50 test leads. | K9: Structured extraction library with Pydantic models, JSON schema validation, and token cost counter. | L9: 100% valid JSON output compliance over 100 test cases using native structured output modes. | M9: OpenAI Structured Outputs Guide, Gemini API Cookbook, Anthropic Prompt Engineering Interactive Tutorial | N9: Not Started
A10: 6 | B10: Embeddings, Vector Databases & RAG | C10: Construct enterprise-grade Retrieval-Augmented Generation pipelines grounded in private product documentation. | D10: Embedding models (text-embedding-3, BGE, Voyage), Chunking strategies (fixed, semantic, recursive, markdown), Vector similarity (Cosine, Dot Product), Vector databases (ChromaDB, pgvector), Hybrid Search (Dense + Sparse BM25), Reranking (Cohere, Cross-Encoder), Grounding & Citations, RAG Evaluation (RAGAS / TruLens). | E10: Phase 5: LLM APIs, Python | F10: 2027-03-26 | G10: 2027-04-30 | H10: 70 | I10: 0 | J10: 1. Build document ingestion pipeline with semantic chunking. 2. Set up PostgreSQL with pgvector for persistent vector search. 3. Implement hybrid search with cross-encoder reranking. | K10: Project 4: Enterprise Product Knowledge Assistant using RAG with citation grounding and evaluation notebook. | L10: Zero hallucination on factual product specifications; retrieval precision > 88% on domain test benchmark. | M10: LangChain / LlamaIndex docs, Pinecone Learning Center, pgvector documentation | N10: Not Started
A11: 7 | B11: AI Agent Fundamentals & Tool Calling | C11: Learn core agentic patterns: reasoning loops, tool calling schemas, environment execution, and state persistence. | D11: Agent Architectures (ReAct, Plan-and-Solve, Reflection), Function Calling / Tool Calling schemas, Tool argument validation with Pydantic, Memory design (short-term buffer, long-term vector/SQL), Execution sandboxing, State persistence, Error recovery & tool retries. | E11: Phase 5 & 6: Structured Outputs, LLM APIs, Vector Stores | F11: 2027-05-01 | G11: 2027-05-31 | H11: 75 | I11: 0 | J11: 1. Build ReAct agent loop from scratch in pure Python. 2. Equip agent with tools: web search, calculator, SQL query, CRM contact lookup. 3. Implement persistent SQLite session state. | K11: Project 5: Tool-Using Autonomous Research Agent capable of multi-step company research. | L11: Agent successfully completes 3-step tool chains with proper parameter passing and zero execution crashes. | M11: OpenAI Function Calling Guide, Anthropic Building Effective Agents, LangGraph official tutorials | N11: Not Started
A12: 8 | B12: Agent Orchestration & Multi-Agent Systems | C12: Orchestrate complex workflows, human-in-the-loop approvals, and specialized multi-agent collaboration. | D12: State Graphs with LangGraph, Multi-Agent patterns (Supervisor, Hierarchical, Peer-to-Peer), CrewAI framework, Conditional routing, Dynamic replanning, Human-in-the-loop (HITL) checkpoints & approval gates, Guardrails (NeMo Guardrails, Llama Guard), Context distillation. | E12: Phase 7: Tool Calling & Agent Fundamentals | F12: 2027-06-01 | G12: 2027-06-30 | H12: 75 | I12: 0 | J12: 1. Build a LangGraph workflow with human-approval checkpoint before sending email. 2. Create 3-agent team: Lead Researcher, Email Drafter, Quality Reviewer. 3. Implement fallback routing when primary tool fails. | K12: Project 6: Lead Qualification & Scoring Agent + Project 9: Collaborative Multi-Agent Sales Workflow. | L12: Multi-agent workflow handles unexpected tool failure gracefully and pauses execution for human approval on high-value actions. | M12: LangGraph Documentation, CrewAI Masterclass, Llama Guard docs | N12: Not Started
A13: 9 | B13: AI Sales Agent Development (Autonomous Sales Employee) | C13: Synthesize all agentic capabilities into a dedicated, commercial-grade AI Sales Employee. | D13: 12 Core Capabilities: Prospecting, BANT Lead Scoring, Consultative Needs Discovery, Multi-channel Communication (Email/Chat/WhatsApp), Knowledge RAG, Price Negotiation within business guardrails, Automated Follow-up sequences, PDF Quotation generation, CRM synchronization (HubSpot/Postgres), Analytics logging, Human escalation triggers. | E13: Phases 6, 7, 8: RAG, Tool Calling, Orchestration | F13: 2027-07-01 | G13: 2027-08-15 | H13: 95 | I13: 0 | J13: 1. Build BANT scoring engine that scores leads from conversation transcripts. 2. Implement price negotiation agent with strict discount ceilings. 3. Connect agent to WhatsApp Business sandbox and SendGrid email API. | K13: Project 7: AI Sales Employee with Follow-ups & Project 8: AI Negotiation and Quotation Assistant. | L13: End-to-end simulated customer engagement: agent researches lead, answers questions from RAG, qualifies budget, negotiates price within policy, and outputs signed quote. | M13: HubSpot API Docs, Meta WhatsApp Cloud API Docs, ReportLab PDF documentation | N13: Not Started
A14: 10 | B14: Model Fine-Tuning & Customization | C14: Master when and how to fine-tune open-weight and proprietary models for domain-specific sales style and cost reduction. | D14: When to Prompt vs RAG vs Fine-tune, Dataset preparation & formatting (ShareGPT, Alpaca, JSONL), Parameter-Efficient Fine-Tuning (PEFT, LoRA, QLoRA), SFT (Supervised Fine-Tuning) with TRL / Unsloth, Evaluation with benchmark test suites, Model merging and GGUF export. | E14: Phase 4 & Phase 3: PyTorch, Transformer basics, Quantization | F14: 2027-08-16 | G14: 2027-09-15 | H14: 60 | I14: 0 | J14: 1. Format 500 sales objection-handling pairs into JSONL. 2. Fine-tune Llama-3-8B with QLoRA using Unsloth on Google Colab / Lambda Labs. 3. Compare fine-tuned model vs prompt-engineered base model on benchmark set. | K14: Fine-tuned specialized sales objection-handling adapter, training loss curves, and evaluation comparison report. | L14: Fine-tuned model achieves > 92% adherence to company sales methodology with 3x lower inference cost than frontier APIs. | M14: Hugging Face PEFT & TRL docs, Unsloth documentation, Axolotl GitHub | N14: Not Started
A15: 11 | B15: Production Deployment, Security & Monitoring | C15: Engineer reliable, secure, containerized cloud infrastructure for real business usage. | D15: FastAPI async backend, Docker containerization, PostgreSQL database design, Redis message queuing & background tasks, Authentication & API keys, Observability (LangSmith / OpenLLMetry / Arize Phoenix), Rate limiting & token quotas, Security (OWASP Top 10 for LLMs, Prompt Injection, Data Leakage). | E15: Phase 1 (Python, Linux, Git) & Backend familiarity | F15: 2027-09-16 | G15: 2027-10-15 | H15: 70 | I15: 0 | J15: 1. Dockerize full agent system with docker-compose (FastAPI, Redis, Postgres, pgvector). 2. Instrument agent with OpenTelemetry tracing and LangSmith dashboard. 3. Add prompt injection sanitization layer and rate limiter. | K15: Project 10: Production-Ready AI Sales Platform deployed on Render / Hetzner with healthchecks and monitoring. | L15: Server maintains 99.5% uptime under simulated load test; zero token quota leaks; full trace visibility on all agent decisions. | M15: Docker Docs, FastAPI Production Guide, OWASP LLM Top 10, LangSmith Docs | N15: Not Started
A16: 12 | B16: Advanced AI Engineering & Commercialization | C16: Package, market, and commercially sell specialized AI agents to business clients. | D16: Product-Market Fit for AI agents, Commercial pricing models (per-agent seat vs usage/success fee), Client onboarding workflows, Multi-tenant data segregation, Sales demos & interactive landing pages, SLA definitions, Customer feedback loops, Maintenance & ongoing agent retraining. | E16: All previous phases: Full working product | F16: 2027-10-16 | G16: 2027-10-31 | H16: 65 | I16: 0 | J16: 1. Draft commercial SaaS terms & SLA agreement for AI Sales Employee. 2. Build interactive public demo on Render / Vercel. 3. Conduct 5 customer discovery interviews with sales agency leaders. | K16: Live commercial offering: Landing page, documentation, interactive sales demo, and validated pricing packages. | L16: Secure at least 1 pilot business customer or formal letter of intent (LOI) to deploy AI Sales Employee. | M16: Y Combinator Startup School, Stripe Billing Docs, Commercial Product Validation Sheet | N16: Not Started
A17: TOTAL CURRICULUM HOURS | H17: =SUM(H5:H16) | I17: =SUM(I5:I16)

Sheet Detailed Learning Tracker
A1: DETAILED LEARNING SESSION TRACKER
A2: Granular Session Log: Tracking Planned vs Actual Hours, Confidence, Evidence, Retention & Retrospective Analysis
A4: Learning ID | B4: Date | C4: Phase | D4: Subject | E4: Topic | F4: Subtopic | G4: Learning Objective | H4: Importance | I4: Prerequisites | J4: Resource ID | K4: Resource URL | L4: Resource Type | M4: Planned Duration (hrs) | N4: Actual Duration (hrs) | O4: Completion % | P4: Current Status | Q4: Confidence (1-5) | R4: Assessment Score (%) | S4: Practical Exercise Completed | T4: GitHub / Evidence Link | U4: Key Lessons Learned | V4: Questions or Difficulties | W4: Next Action | X4: Review Date | Y4: Completion Date
A5: LRN-001 | B5: 2026-11-01 | C5: Phase 1 | D5: Python | E5: Data Structures & OOP | F5: Classes, Dunder methods, TypedDict | G5: Master Python OOP design patterns and type hints for AI agent state representations | H5: High | I5: Python basics | J5: RES-017 | K5: https://docs.python.org/3/tutorial/classes.html | L5: Official Doc | M5: 3 | N5: 0 | O5: 0 | P5: Not Started | Q5: 3 | S5: No | W5: Code custom Pydantic-style class with validation | X5: 2026-11-04
A6: LRN-002 | B6: 2026-11-03 | C6: Phase 1 | D6: Python | E6: API & JSON Serialization | F6: requests, httpx, json module, Pydantic | G6: Build robust async API fetchers with automatic JSON deserialization and error retry loops | H6: High | I6: LRN-001 | J6: RES-022 | K6: https://fastapi.tiangolo.com/tutorial/body/ | L6: Documentation | M6: 2.5 | N6: 0 | O6: 0 | P6: Not Started | Q6: 3 | S6: No | W6: Build CLI weather fetcher with exponential backoff | X6: 2026-11-07
A7: LRN-003 | B7: 2026-11-05 | C7: Phase 1 | D7: Mathematics | E7: Linear Algebra | F7: Vectors, Dot products, Matrix Multiplication | G7: Understand vector geometry and matrix operations essential for embeddings and attention layers | H7: High | I7: High school math | J7: RES-018 | K7: https://numpy.org/doc/stable/user/quickstart.html | L7: Course/Doc | M7: 3.5 | N7: 0 | O7: 0 | P7: Not Started | Q7: 2 | S7: No | W7: Implement 2D and 3D matrix multiply without external libraries | X7: 2026-11-10
A8: LRN-004 | B8: 2026-11-08 | C8: Phase 1 | D8: Mathematics | E8: Probability & Statistics | F8: Normal distribution, Bayes Theorem, Hypothesis Testing | G8: Develop statistical intuition for model confidence scores and A/B test lead conversions | H8: Medium | I8: LRN-003 | J8: RES-001 | K8: https://developers.google.com/machine-learning/crash-course | L8: Course | M8: 3 | N8: 0 | O8: 0 | P8: Not Started | Q8: 2 | S8: No | W8: Calculate conditional probability of lead conversion using Bayes rule | X8: 2026-11-14
A9: LRN-005 | B9: 2026-11-12 | C9: Phase 1 | D9: Mathematics | E9: Calculus & Optimization | F9: Partial derivatives, Gradients, Chain Rule | G9: Understand loss landscapes and how gradient descent updates weights in ML models | H9: High | I9: LRN-003 | J9: RES-001 | K9: https://developers.google.com/machine-learning/crash-course | L9: Interactive Tutorial | M9: 3 | N9: 0 | O9: 0 | P9: Not Started | Q9: 2 | S9: No | W9: Write Python script finding minimum of f(x,y)=x^2+2y^2 via gradient descent | X9: 2026-11-18
A10: LRN-006 | B10: 2026-12-01 | C10: Phase 2 | D10: Data Analysis | E10: NumPy & Pandas | F10: Array broadcasting, DataFrame filtering, GroupBy | G10: Master fast vectorized operations and sales dataset manipulation using Pandas | H10: High | I10: LRN-001, LRN-003 | J10: RES-019 | K10: https://pandas.pydata.org/docs/user_guide/ | L10: Official Guide | M10: 3 | N10: 0 | O10: 0 | P10: Not Started | Q10: 3 | S10: No | W10: Analyze 10,000 sales transactions and calculate cohort retention | X10: 2026-12-05
A11: LRN-007 | B11: 2026-12-05 | C11: Phase 2 | D11: Data Analysis | E11: Exploratory Data Analysis | F11: Missing data handling, Outlier detection, Seaborn | G11: Learn to identify data quality anomalies, skewness, and correlations in B2B CRM datasets | H11: Medium | I11: LRN-006 | J11: RES-019 | K11: https://pandas.pydata.org/docs/user_guide/visualization.html | L11: Hands-on Lab | M11: 2.5 | N11: 0 | O11: 0 | P11: Not Started | Q11: 3 | S11: No | W11: Produce correlation heatmap and boxplots for lead response times | X11: 2026-12-09
A12: LRN-008 | B12: 2026-12-10 | C12: Phase 2 | D12: Machine Learning | E12: Supervised Learning | F12: Linear & Logistic Regression, Odds Ratio | G12: Understand regression assumptions, classification boundaries, and sigmoid activation | H12: High | I12: LRN-005, LRN-006 | J12: RES-016 | K12: https://scikit-learn.org/stable/modules/linear_model.html | L12: Official Doc | M12: 3.5 | N12: 0 | O12: 0 | P12: Not Started | Q12: 2 | S12: No | W12: Build customer churn classifier using LogisticRegression with Scikit-learn | X12: 2026-12-15
A13: LRN-009 | B13: 2026-12-16 | C13: Phase 2 | D13: Machine Learning | E13: Tree Ensembles | F13: Decision Trees, Random Forest, XGBoost | G13: Master feature importance, bagging, boosting, and handling non-linear business tabular data | H13: High | I13: LRN-008 | J13: RES-016 | K13: https://scikit-learn.org/stable/modules/ensemble.html | L13: User Guide | M13: 3.5 | N13: 0 | O13: 0 | P13: Not Started | Q13: 2 | S13: No | W13: Train XGBoost classifier predicting whether an inbound lead will book a demo | X13: 2026-12-21
A14: LRN-010 | B14: 2026-12-22 | C14: Phase 2 | D14: Machine Learning | E14: Model Evaluation & Validation | F14: Confusion Matrix, ROC-AUC, F1-score, Cross-Validation | G14: Evaluate classifiers realistically and avoid data leakage in time-series sales pipelines | H14: High | I14: LRN-009 | J14: RES-016 | K14: https://scikit-learn.org/stable/modules/model_evaluation.html | L14: Documentation | M14: 3 | N14: 0 | O14: 0 | P14: Not Started | Q14: 2 | S14: No | W14: Generate precision-recall curve and evaluate cost of false positive sales calls | X14: 2026-12-28
A15: LRN-011 | B15: 2027-01-02 | C15: Phase 3 | D15: Deep Learning | E15: PyTorch Tensors & Autograd | F15: Tensor shapes, GPU tensors, autograd backwards() | G15: Master tensor manipulation, broadcasting rules, and automatic differentiation in PyTorch | H15: High | I15: LRN-003, LRN-005 | J15: RES-014 | K15: https://pytorch.org/tutorials/beginner/basics/tensorqs_tutorial.html | L15: Official Tutorial | M15: 3.5 | N15: 0 | O15: 0 | P15: Not Started | Q15: 2 | S15: No | W15: Write custom linear layer and autograd training loop in PyTorch | X15: 2027-01-06
A16: LRN-012 | B16: 2027-01-08 | C16: Phase 3 | D16: Deep Learning | E16: Neural Network Architectures | F16: MLP, Loss functions, AdamW, Dropout | G16: Build multi-layer perceptron networks, understand learning rate schedules and regularization | H16: High | I16: LRN-011 | J16: RES-014 | K16: https://pytorch.org/tutorials/beginner/basics/buildmodel_tutorial.html | L16: Tutorial | M16: 3.5 | N16: 0 | O16: 0 | P16: Not Started | Q16: 2 | S16: No | W16: Train PyTorch MLP classifying customer inquiries into 5 intent categories | X16: 2027-01-13
... A40: LRN-036 | B40: 2027-09-28 | C40: Phase 11 | D40: Production | E40: LLM Security & OWASP Defense | F40: Prompt injection defenses, Data leakage, Rate limiting | G40: Harden sales agent against adversarial system prompt extraction and unauthorized behavior | H40: High | I40: LRN-018, LRN-024 | J40: RES-025 | K40: https://owasp.org/www-project-top-10-for-large-language-model-applications/ | L40: Security Guide | M40: 3 | N40: 0 | O40: 0 | P40: Not Started | Q40: 2 | S40: No | W40: Implement input sanitizer filter and automated test suite testing 20 injection attacks | X40: 2027-10-05
A41: TOTAL LOGGED HOURS | M41: =SUM(M5:M40) | N41: =SUM(N5:N40)

Sheet Official Learning Resources
A1: CURATED OFFICIAL & AUTHORITATIVE AI/ML RESOURCES
A2: Verified Official Documentation, Cookbooks, Courses & Research Guides from Google, OpenAI, Meta, Hugging Face, PyTorch, and Leading Frameworks
A4: Resource ID | B4: Organization | C4: Resource Title | D4: Official URL | E4: Learning Category | F4: Resource Type | G4: Level | H4: Prerequisites | I4: Recommended Phase | J4: Estimated Duration (hrs) | K4: Free / Paid Status | L4: Importance | M4: Learning Objectives | N4: Practical Exercise | O4: Completion Status | P4: Notes
A5: RES-001 | B5: Google | C5: Google Machine Learning Crash Course | D5: https://developers.google.com/machine-learning/crash-course | E5: Machine Learning | F5: Course / Interactive | G5: Beginner | H5: Python basics | I5: Phase 2 | J5: 15 | K5: Free | L5: Essential | M5: Learn foundational ML concepts, gradient descent, loss functions, classification, and neural network intuitions. | N5: Complete all embedded Colab exercises and model tuning tasks. | O5: Not Started | P5: Excellent visual explanations and interactive TensorFlow/Keras widgets.
A6: RES-002 | B6: Google | C6: Google Foundational ML & Data Prep Courses | D6: https://developers.google.com/machine-learning/data-prep | E6: Data Engineering | F6: Course / Guide | G6: Beginner to Intermediate | H6: Python, Statistics | I6: Phase 2 | J6: 10 | K6: Free | L6: Recommended | M6: Master data transformation, feature scaling, numerical bucketing, categorical encoding, and handling missing values. | N6: Clean an uncurated customer dataset and transform features for regression modeling. | O6: Not Started | P6: Official Google guidance on real-world ML data hygiene.
A7: RES-003 | B7: Google | C7: Google Gemini API Documentation | D7: https://ai.google.dev/docs | E7: LLM APIs | F7: Official Documentation | G7: Intermediate | H7: REST APIs, Python | I7: Phase 5 | J7: 8 | K7: Free / Freemium | L7: Essential | M7: Learn Gemini model families (Flash, Pro), multimodal inputs, system instructions, safety settings, and token limits. | N7: Build a Python client calling Gemini-1.5-Flash with custom safety thresholds and system prompt. | O7: Not Started | P7: Free tier offers generous rate limits for rapid prototyping.
A8: RES-004 | B8: Google | C8: Google Gemini API Cookbook | D8: https://github.com/google-gemini/cookbook | E8: LLM Applications | F8: Repository / Cookbook | G8: Intermediate | H8: Python, Gemini API | I8: Phase 5 & 6 | J8: 12 | K8: Free | L8: Essential | M8: Practical recipe code for RAG, function calling, structured extraction, audio/video analysis, and document reasoning. | N8: Implement the official function calling and structured JSON output notebook recipes. | O8: Not Started | P8: Maintained directly by Google AI Developer Relations.
A9: RES-005 | B9: OpenAI | C9: OpenAI Developer Platform Documentation | D9: https://platform.openai.com/docs | E9: LLM APIs | F9: Official Documentation | G9: Beginner to Intermediate | H9: REST APIs, JSON | I9: Phase 5 | J9: 10 | K9: Paid API | L9: Essential | M9: Understand Chat Completions, context windows, seed parameters, role system, streaming responses, and token usage. | N9: Create multi-turn chat wrapper handling token limits and streaming outputs to terminal. | O9: Not Started | P9: The industry benchmark API standard for commercial LLM integration.
A10: RES-006 | B10: OpenAI | C10: OpenAI Function Calling Guide | D10: https://platform.openai.com/docs/guides/function-calling | E10: AI Agents | F10: Official Guide | G10: Intermediate | H10: Python, JSON Schema | I10: Phase 7 | J10: 8 | K10: Paid API | L10: Essential | M10: Learn strict tool schemas, parallel tool calls, tool choice parameters, and executing function responses. | N10: Build agent with 3 simulated business tools: CRM lookup, inventory query, discount calculator. | O10: Not Started | P10: Critical foundation for all agentic workflows.
A11: RES-007 | B11: OpenAI | C11: OpenAI Structured Outputs Guide | D11: https://platform.openai.com/docs/guides/structured-outputs | E11: LLM Applications | F11: Official Guide | G11: Intermediate | H11: Pydantic, JSON Schema | I11: Phase 5 | J11: 6 | K11: Paid API | L11: Essential | M11: Master 100% reliable schema adherence with constrained decoding and native Pydantic integration. | N11: Extract validated lead BANT qualification objects directly from messy sales call transcripts. | O11: Not Started | P11: Eliminates need for retry loops due to malformed JSON.
A12: RES-008 | B12: OpenAI | C12: OpenAI Retrieval, Evals & Agent Building Guide | D12: https://platform.openai.com/docs/guides/evals | E12: Evaluation & Agents | F12: Guide / Framework | G12: Advanced | H12: Python, LLM APIs | I12: Phase 7 & 11 | J12: 12 | K12: Free / Paid API | L12: Recommended | M12: Learn rigorous LLM evaluation methodologies, synthetic dataset creation, and agent benchmarking. | N12: Build an automated evaluation pipeline measuring sales agent response accuracy against 30 gold standards. | O12: Not Started | P12: Essential for verifying capability before selling to clients.
A13: RES-009 | B13: Meta | C13: Meta Llama Documentation & Model Card | D13: https://llama.meta.com/docs | E13: Open-Weight LLMs | F13: Official Documentation | G13: Intermediate to Advanced | H13: Linux, Python | I13: Phase 4 & 10 | J13: 10 | K13: Free | L13: Essential | M13: Understand Llama-3 architecture, tokenizer nuances, prompt formatting, context window expansion, and licensing terms. | N13: Download and verify Llama-3-8B weights on Ubuntu Linux environment. | O13: Not Started | P13: Premier open-weight model family for local and cost-effective commercial deployment.
A14: RES-010 | B14: Meta | C14: Meta Llama Cookbook | D14: https://github.com/meta-llama/llama-cookbook | E14: LLM Engineering | F14: Repository / Cookbook | G14: Intermediate to Advanced | H14: Python, PyTorch | I14: Phase 6 & 10 | J14: 15 | K14: Free | L14: Essential | M14: Production code for local inference with vLLM/Ollama, fine-tuning with PEFT, synthetic data, and RAG pipelines. | N14: Run end-to-end local RAG pipeline with Llama-3-8B and ChromaDB. | O14: Not Started | P14: Official Meta repository with battle-tested engineering notebooks.
A15: RES-011 | B15: Meta | C15: Meta Llama Fine-Tuning & Quantization Guide | D15: https://github.com/meta-llama/llama-recipes | E15: Fine-Tuning | F15: Cookbook / Guide | G15: Advanced | H15: PyTorch, CUDA, PEFT | I15: Phase 10 | J15: 14 | K15: Free (Compute Req) | L15: Recommended | M15: Learn LoRA, QLoRA, FSDP distributed training, and quantizing Llama models for high-throughput inference. | N15: Fine-tune Llama-3-8B on an objection-handling dataset using QLoRA. | O15: Not Started | P15: Enables adapting open models to proprietary company sales playbooks.
A16: RES-012 | B16: Hugging Face | C16: Hugging Face NLP Course | D16: https://huggingface.co/learn/nlp-course | E16: NLP & Transformers | F16: Interactive Course | G16: Beginner to Intermediate | H16: Python, PyTorch | I16: Phase 3 & 4 | J16: 25 | K16: Free | L16: Essential | M16: Master Transformers from scratch, tokenizers, pipeline API, fine-tuning with Trainer, and evaluation metrics. | N16: Fine-tune a DistilBERT text classification model for customer email urgency detection. | O16: Not Started | P16: Widely recognized as the best practical deep dive into modern NLP.
... A29: RES-025 | B29: OWASP | C29: OWASP Top 10 for Large Language Model Applications | D29: https://owasp.org/www-project-top-10-for-large-language-model-applications/ | E29: AI Security | F29: Security Guide | G29: Intermediate to Advanced | H29: LLM basics | I29: Phase 11 | J29: 6 | K29: Free | L29: Essential | M29: Prompt injection, insecure output handling, training data poisoning, model denial of service, excessive agency. | N29: Audit your sales agent against all 10 vulnerabilities and implement sanitization & tool permission boundaries. | O29: Not Started | P29: Non-negotiable security requirements before exposing agents to commercial clients.

Sheet Topic Completion Checklist
A1: AI/ML & AI AGENT TOPIC COMPLETION CHECKLIST
A2: Granular Skill-by-Skill Verification: Python, Mathematics, ML, DL, LLMs, RAG, Agents, Production, and Business
A4: Topic ID | B4: Subject | C4: Topic Name | D4: Priority | E4: Prerequisites | F4: Resource Links | G4: Status | H4: Confidence Score (1-5) | I4: Practice Task | J4: Assessment Criteria | K4: Evidence | L4: Date Completed | M4: Notes
A5: TOP-001 | B5: Python | C5: Variables & Advanced Data Types | D5: High | E5: Basic syntax | F5: RES-017 | G5: Not Started | H5: 3 | I5: Implement custom cache dict with TTL expiration using Python dict & time. | J5: Explain memory references vs copies and mutability nuances.
A6: TOP-002 | B6: Python | C6: Functions, Closures & Decorators | D6: High | E6: TOP-001 | F6: RES-017 | G6: Not Started | H6: 3 | I6: Build `@retry_with_backoff(max_retries=3)` decorator for API calls. | J6: Decorator properly wraps async/sync functions with functools.wraps.
A7: TOP-003 | B7: Python | C7: OOP, Protocols & Abstract Classes | D7: High | E7: TOP-002 | F7: RES-017 | G7: Not Started | H7: 3 | I7: Design abstract BaseAgent class and implement EmailSalesAgent subclass. | J7: Demonstrate polymorphism, dependency injection, and clean interface segregation.
A8: TOP-004 | B8: Python | C8: Exception Handling & Custom Errors | D8: High | E8: TOP-003 | F8: RES-017 | G8: Not Started | H8: 3 | I8: Create hierarchy: AgentError -> ToolExecutionError -> RateLimitExceededError. | J8: Code handles specific exceptions cleanly without catching broad Exception.
A9: TOP-005 | B9: Python | C9: JSON, Serialization & Pydantic | D9: High | E9: TOP-001 | F9: RES-017 | G9: Not Started | H9: 3 | I9: Build Pydantic schema for LeadProfile with email and phone validator. | J9: Validates nested schemas and rejects malformed types gracefully.
A10: TOP-006 | B10: Python | C10: AsyncIO & Concurrent HTTP Fetching | D10: High | E10: TOP-002 | F10: RES-022 | G10: Not Started | H10: 2 | I10: Use httpx.AsyncClient to query 20 website homepages concurrently. | J10: Runs without blocking event loop; handles timeouts and connection errors.
A11: TOP-007 | B11: Python | C11: File I/O & JSONL Streaming | D11: Medium | E11: TOP-001 | F11: RES-017 | G11: Not Started | H11: 3 | I11: Stream 100,000 JSON lines without loading entire file into memory. | J11: Uses generator functions yielding records one line at a time.
A12: TOP-008 | B12: Python | C12: Virtual Environments & Poetry/Pip | D12: High | E12: None | F12: RES-017 | G12: Not Started | H12: 3 | I12: Configure clean Python 3.11 virtual environment with lockfile. | J12: Installs cleanly on clean Ubuntu machine without dependency conflicts.
A13: TOP-009 | B13: Python | C13: Unit Testing with Pytest | D13: High | E13: TOP-003 | F13: RES-017 | G13: Not Started | H13: 3 | I13: Write 10 unit tests mocking external LLM responses with pytest-mock. | J13: All tests pass with > 85% branch coverage.
A14: TOP-010 | B14: Python | C14: Structured Logging & Git Discipline | D14: Medium | E14: None | F14: RES-017 | G14: Not Started | H14: 3 | I14: Configure Python `logging` to output JSON formatted logs with timestamps. | J14: Git repo has clean conventional commits and .gitignore for env/keys.
A15: TOP-011 | B15: Mathematics | C15: Vectors, Norms & Dot Products | D15: High | E15: High school math | F15: RES-018 | G15: Not Started | H15: 2 | I15: Write Python function calculating Euclidean L2 norm and Dot Product. | J15: Explain geometric meaning of dot product (projection and angle alignment).
A16: TOP-012 | B16: Mathematics | C16: Matrix Operations & Inversion | D16: High | E16: TOP-011 | F16: RES-018 | G16: Not Started | H16: 2 | I16: Multiply (4x3) matrix by (3x2) matrix by hand and in Python. | J16: Understand row-column compatibility and why inversion can be unstable.
... A56: TOP-052 | B56: Business | C56: Commercial SaaS Pricing & Unit Economics | D56: High | E56: None | F56: RES-020 | G56: Not Started | H56: 2 | I56: Calculate token API costs, server costs, and target 80% gross profit margins. | J56: Establish sustainable pricing: e.g. $499/mo per autonomous sales seat.

Sheet Tutorial and Course Tracker
A1: TUTORIAL, COURSE & PAPER STUDY TRACKER
A2: Tracking Guided Learning: Videos, Courses, Interactive Labs, and Research Papers with Enforced Practical Deliverables
A4: Tutorial ID | B4: Title | C4: Provider | D4: URL | E4: Subject | F4: Difficulty | G4: Format | H4: Estimated Duration (hrs) | I4: Actual Duration (hrs) | J4: Start Date | K4: Completion Date | L4: Current Status | M4: Important Lessons | N4: Exercises Completed | O4: Personal Rating (1-5) | P4: Notes
A5: TUT-001 | B5: Python for Everybody Specialization | C5: Coursera / Dr. Chuck | D5: https://www.py4e.com/ | E5: Python | F5: Beginner | G5: Course | H5: 20 | I5: 0 | J5: 2026-11-01 | L5: Not Started | M5: Data structures, web scraping, SQL databases, and JSON APIs in Python. | N5: Exercises 1-10 completed | P5: Review Python fundamentals and clean design patterns.
A6: TUT-002 | B6: Essence of Linear Algebra | C6: 3Blue1Brown | D6: https://www.3blue1brown.com/topics/linear-algebra | E6: Mathematics | F6: Beginner | G6: Video Series | H6: 6 | I6: 0 | J6: 2026-11-05 | L6: Not Started | M6: Geometric intuition behind matrices as linear transformations and eigenvectors. | N6: Visualized matrix transforms in Python | P6: Must-watch visual series to deeply understand dot products and projections.
A7: TUT-003 | B7: Google Machine Learning Crash Course | C7: Google | D7: https://developers.google.com/machine-learning/crash-course | E7: Machine Learning | F7: Beginner to Intermediate | G7: Interactive Course | H7: 15 | I7: 0 | J7: 2026-12-01 | L7: Not Started | M7: Gradient descent, loss surfaces, classification metrics, and regularization. | N7: All Colab programming exercises | P7: High quality visual explanations of machine learning principles.
A8: TUT-004 | B8: Deep Learning with PyTorch: A 60 Minute Blitz | C8: PyTorch Official | D8: https://pytorch.org/tutorials/beginner/deep_learning_60min_blitz.html | E8: Deep Learning | F8: Intermediate | G8: Hands-on Lab | H8: 4 | I8: 0 | J8: 2027-01-02 | L8: Not Started | M8: Tensors, autograd engine, building neural networks with nn.Module, and optimizers. | N8: Built and trained mini CNN on CIFAR-10 | P8: Official PyTorch onboarding module. Short, dense, and effective.
A9: TUT-005 | B9: Neural Networks: Zero to Hero (micrograd & makemore) | C9: Andrej Karpathy | D9: https://karpathy.ai/zero-to-hero.html | E9: Deep Learning | F9: Intermediate | G9: Video / Code-along | H9: 16 | I9: 0 | J9: 2027-01-10 | L9: Not Started | M9: Built autograd engine from scratch, backprop math, and character-level language models. | N9: Implemented micrograd engine in Python | P9: The gold standard for demystifying backpropagation and neural net training.
A10: TUT-006 | B10: Hugging Face Transformers Course (Chapters 1-4) | C10: Hugging Face | D10: https://huggingface.co/learn/nlp-course | E10: LLMs & NLP | F10: Intermediate | G10: Interactive Course | H10: 12 | I10: 0 | J10: 2027-02-02 | L10: Not Started | M10: Tokenizers, pipelines, attention mechanisms, and fine-tuning with Trainer. | N10: Fine-tuned text classifier on customer tickets | P10: Essential practical grounding for open-source LLM manipulation.
A11: TUT-007 | B11: Attention Is All You Need (Paper Walkthrough) | C11: Vaswani et al. / Jay Alammar | D11: https://jalammar.github.io/illustrated-transformer/ | E11: LLMs | F11: Intermediate to Advanced | G11: Paper & Visual Guide | H11: 5 | I11: 0 | J11: 2027-02-10 | L11: Not Started | M11: Scaled dot-product attention equation, query-key-value transformations, positional encodings. | N11: Annotated Transformer architecture diagram | P11: Foundational paper that launched modern Generative AI.
A12: TUT-008 | B12: ChatGPT Prompt Engineering for Developers | C12: DeepLearning.AI / OpenAI | D12: https://www.deeplearning.ai/short-courses/chatgpt-prompt-engineering-for-developers/ | E12: Prompting | F12: Beginner | G12: Short Course | H12: 2 | I12: 0 | J12: 2027-03-02 | L12: Not Started | M12: System messages, delimiters, structured JSON extraction, and iterative prompt design. | N12: Built lead data extraction prompts in Jupyter | P12: Taught by Isa Fulford (OpenAI) and Andrew Ng.
A13: TUT-009 | B13: Building Systems with the ChatGPT API | C13: DeepLearning.AI / OpenAI | D13: https://www.deeplearning.ai/short-courses/building-systems-with-chatgpt/ | E13: LLM Systems | F13: Intermediate | G13: Short Course | H13: 2.5 | I13: 0 | J13: 2027-03-08 | L13: Not Started | M13: Chaining prompts, moderation API, input evaluation, and user interaction loops. | N13: Built multi-step customer service bot | P13: Focuses on safety and evaluating system outputs.
A14: TUT-010 | B14: LangGraph: Developing Multi-Agent Applications | C14: LangChain Academy | D14: https://academy.langchain.com/ | E14: AI Agents | F14: Intermediate to Advanced | G14: Course / Labs | H14: 10 | I14: 0 | J14: 2027-05-02 | L14: Not Started | M14: StateGraph, cyclical agent loops, persistence checkpoints, and conditional routing. | N14: Built stateful research agent with human-in-the-loop | P14: The definitive course on reliable agentic architecture.
A15: TUT-011 | B15: Functions, Tools and Agents with LangChain | C15: DeepLearning.AI / Harrison Chase | D15: https://www.deeplearning.ai/short-courses/functions-tools-agents-langchain/ | E15: AI Agents | F15: Intermediate | G15: Short Course | H15: 3 | I15: 0 | J15: 2027-05-12 | L15: Not Started | M15: OpenAI function calling, tool binding, routing, and ReAct agent workflows. | N15: Created agent invoking weather and CRM tools | P15: Excellent practical introduction to function calling.
A16: TUT-012 | B16: Building Agentic RAG with LlamaIndex | C16: DeepLearning.AI / Jerry Liu | D16: https://www.deeplearning.ai/short-courses/building-agentic-rag-with-llamaindex/ | E16: RAG & Agents | F16: Intermediate | G16: Short Course | H16: 3 | I16: 0 | J16: 2027-06-02 | L16: Not Started | M16: Router engines, sub-question query planning, and tool-augmented document retrieval. | N16: Built router querying both SQL DB and vector docs | P16: Bridges document retrieval with agentic decision-making.
... A20: TUT-016 | B20: Docker for Developers | C20: freeCodeCamp / TechWorld with Nana | D20: https://www.youtube.com/watch?v=3c-iBn73dDE | E20: DevOps | F20: Intermediate | G20: Video & Hands-on | H20: 5 | I20: 0 | J20: 2027-09-24 | L20: Not Started | M20: Container isolation, volumes, networks, Dockerfiles, and multi-container Docker Compose. | N20: Containerized FastAPI app with Postgres and Redis | P20: Crucial for reliable deployments on Render and Hetzner.
A21: TOTAL TUTORIAL HOURS | H21: =SUM(H5:H20) | I21: =SUM(I5:I20)

Sheet AI Project Backlog
A1: AI PROJECT BACKLOG & PRACTICAL PORTFOLIO ROADMAP
A2: 10 Practical Milestones Progressing from Core Data Science to an Autonomous, Commercial-Grade AI Sales Employee Platform
A4: Project ID | B4: Project Name | C4: Business Problem | D4: Learning Phase | E4: Required Skills | F4: Technology Stack | G4: Feature List | H4: Prerequisites | I4: Tasks and Subtasks | J4: Target Date | K4: Status | L4: Priority | M4: Estimated Effort (hrs) | N4: Actual Effort (hrs) | O4: Acceptance Criteria | P4: Testing Requirements | Q4: GitHub Repository | R4: Demo URL | S4: Known Risks | T4: Lessons Learned / Next Milestone
A5: PRJ-001 | B5: Sales Data Analysis & Customer Segmentation | C5: Sales teams lack visibility into which customer segments generate the highest lifetime value and have the shortest sales cycles. | D5: Phase 2 | E5: Data cleaning, feature engineering, statistical aggregation, exploratory visualization | F5: Python, Pandas, NumPy, Matplotlib, Seaborn, Jupyter Notebook | G5: 1. Automated ingestion of raw CRM transaction CSVs. 2. Customer RFM (Recency, Frequency, Monetary) segmentation. 3. Sales pipeline velocity calculation by industry. 4. Correlation matrix and interactive cohort heatmaps. | H5: Phase 1 Python & statistics | I5: 1. Data hygiene & outlier treatment. 2. Calculate RFM scores. 3. Segment customers into 4 quartiles. 4. Produce markdown executive summary. | J5: 2026-12-20 | K5: Not Started | L5: High | M5: 25 | N5: 0 | O5: Clean reproducible Jupyter notebook producing RFM segments, visual charts, and actionable sales recommendations without execution errors. | P5: Pytest asserting data cleaning functions handle NaNs and duplicate transaction IDs properly. | Q5: https://github.com/tasim/sales-data-segmentation | S5: Missing transaction records and dirty timestamp formats in real-world CRM extracts. | T5: Mastered vectorized Pandas operations and business KPI definitions.
A6: PRJ-002 | B6: Customer Purchase Prediction Model | C6: Sales reps waste 60% of their time calling cold leads who have almost zero probability of purchasing enterprise software. | D6: Phase 2 | E6: Supervised classification, feature scaling, model selection, hyperparameter tuning, metric evaluation | F6: Python, Scikit-Learn, XGBoost, Pandas, Joblib | G6: 1. Feature pipeline transforming categorical company data and engagement signals. 2. Trained XGBoost classifier predicting purchase probability. 3. Threshold optimizer prioritizing high-precision lead calling. 4. Exportable scoring pipeline function. | H6: PRJ-001, Scikit-learn basics | I6: 1. Feature selection & train/test split. 2. Address class imbalance with SMOTE/class weights. 3. Grid search hyperparameter tuning. 4. Save trained pipeline to .joblib. | J6: 2026-12-31 | K6: Not Started | L6: High | M6: 30 | N6: 0 | O6: Classifier achieves ROC-AUC > 0.85 and Precision > 75% on held-out test split, outperforming naive baseline by 3x. | P6: Cross-validation verification asserting zero feature leakage between train and test folds. | Q6: https://github.com/tasim/lead-purchase-predictor | S6: Overfitting to historical data due to shifting customer behavior seasonality. | T6: Learned how to set decision thresholds based on actual sales call labor cost.
A7: PRJ-003 | B7: Customer Message Intent & Urgency Classifier | C7: Customer inquiries arrive in high volume across email and chat without automated routing to appropriate specialists. | D7: Phase 3 | E7: Neural network architecture, text tokenization, embeddings, PyTorch training loop | F7: Python, PyTorch, Hugging Face Tokenizers, Scikit-Learn | G7: 1. Multi-class text classification into: Demo Request, Pricing Inquiry, Technical Question, Complaint, General Info. 2. Secondary binary classifier for High Urgency vs Normal. 3. PyTorch inference class returning probabilities and confidence scores. | H7: Phase 3 PyTorch basics | I7: 1. Dataset labeling and preprocessing. 2. Implement PyTorch MLP with embedding layer. 3. Training loop with early stopping. 4. Evaluate confusion matrix. | J7: 2027-01-25 | K7: Not Started | L7: Medium | M7: 35 | N7: 0 | O7: Model achieves Macro F1 > 0.84 across 5 intent classes on 1,000 test messages. | P7: Unit tests asserting model handles empty strings, emojis, and very long text inputs gracefully. | Q7: https://github.com/tasim/customer-intent-classifier | S7: Ambiguous multi-intent messages (e.g. asking both about pricing and filing a technical bug). | T7: Understood internal mechanics of PyTorch tensors, autograd, and classification loss functions.
A8: PRJ-004 | B8: Product Knowledge Assistant using RAG | C8: Sales reps and potential buyers struggle to find accurate technical specifications and pricing details buried in 200-page product catalogs. | D8: Phase 6 | E8: Document chunking, vector embeddings, vector databases, hybrid retrieval, citation grounding | F8: Python, FastAPI, pgvector, PostgreSQL, LangChain/LlamaIndex, OpenAI/Gemini Embeddings | G8: 1. Automated PDF/Markdown catalog ingestion pipeline. 2. Semantic chunking with page and section metadata. 3. Hybrid search (Dense cosine similarity + BM25 keyword search). 4. Verified citation generation with page number references. | H8: Phase 5 LLM APIs, Phase 6 Vector stores | I8: 1. Set up Docker PostgreSQL pgvector. 2. Chunk company product manuals. 3. Ingest embeddings. 4. Build RAG retrieval query pipeline. 5. Benchmark retrieval precision. | J8: 2027-04-20 | K8: Not Started | L8: High | M8: 40 | N8: 0 | O8: Answers factual product questions with 100% citation accuracy; refuses out-of-domain questions with zero hallucination. | P8: Automated test suite using RAGAS asserting Faithfulness > 0.90 and Answer Relevance > 0.88. | Q8: https://github.com/tasim/product-knowledge-rag | S8: Chunk boundary splitting that separates pricing table headers from price values. | T8: Learned importance of hybrid search for exact product SKU numbers.
A9: PRJ-005 | B9: Tool-Using Autonomous Research Agent | C9: Pre-call prospect research requires manual searching across LinkedIn, Google, company websites, and CRM systems, taking 30 minutes per lead. | D9: Phase 7 | E9: Tool calling schemas, ReAct loop, Pydantic validation, external API consumption | F9: Python, OpenAI Function Calling, Tavily Search API, Pydantic, Requests | G9: 1. Custom ReAct reasoning loop in pure Python. 2. 4 Tools: `search_company_web`, `get_crm_account`, `calculate_market_size`, `save_lead_summary`. 3. Automated lead dossier generation in structured Markdown format. | H9: Phase 5 Structured Outputs, Phase 7 Tools | I9: 1. Define tool schemas with Pydantic. 2. Implement execution dispatcher. 3. Build autonomous ReAct loop with max iteration limits. 4. Output formatted executive briefing. | J9: 2027-05-25 | K9: Not Started | L9: High | M9: 35 | N9: 0 | O9: Agent independently executes 3-4 tool calls in sequence to research an unfamiliar company and outputs complete structured lead profile. | P9: Mocked API tests verifying tool call failure recovery and circuit breaking after 5 iterations. | Q9: https://github.com/tasim/autonomous-research-agent | S9: Infinite loops when LLM cannot find answer from web search results. | T9: Built robust tool parameter validation and error feedback loops.
A10: PRJ-006 | B10: Lead Qualification & BANT Scoring Agent | C10: Inbound leads receive generic follow-ups because sales teams cannot interview every prospect to establish Budget, Authority, Need, and Timing. | D10: Phase 8 | E10: State machines, LangGraph, conversational steering, deterministic scoring algorithms | F10: Python, LangGraph, Pydantic, SQLite persistence | G10: 1. Consultative conversation graph that naturally asks qualifying questions. 2. Dynamic BANT score updater (0-100 points). 3. Automatic categorization into Hot, Warm, Cold. 4. SQLite thread state persistence across conversational pauses. | H10: PRJ-004, PRJ-005, LangGraph basics | I10: 1. Define StateGraph schema. 2. Implement qualification nodes. 3. Build BANT scoring logic. 4. Add SQLite checkpointer. | J10: 2027-06-25 | K10: Not Started | L10: High | M10: 45 | N10: 0 | O10: Agent sustains multi-turn conversation, gathers all 4 BANT criteria without sounding robotic, and calculates accurate qualification score. | P10: Simulated conversation test suite running 20 distinct buyer personas through qualification flow. | Q10: https://github.com/tasim/lead-qualification-agent | S10: Prospects resisting budget questions or giving evasive answers. | T10: Learned consultative prompting techniques to extract business pain before asking about budget.
A11: PRJ-007 | B11: Autonomous AI Sales Employee with Follow-ups | C11: Over 70% of sales opportunities die from poor follow-up cadence; human reps forget to follow up after the first email or message. | D11: Phase 9 | E11: Multi-touch state machine, background scheduling, email & WhatsApp integration, dynamic message personalization | F11: Python, FastAPI, Celery / Redis, PostgreSQL, SendGrid API, WhatsApp Cloud API | G11: 1. Multi-channel messaging (Email + WhatsApp). 2. Stateful follow-up cadence (Day 1, Day 3, Day 7, Day 14). 3. Dynamic message adaptation based on lead opens/clicks. 4. Automatic cadence cancellation when lead replies or books meeting. | H11: PRJ-006, Redis, Celery | I11: 1. Build Celery scheduled task worker. 2. Implement webhook handlers for message replies. 3. Integrate SendGrid and WhatsApp Cloud APIs. 4. Test follow-up state transitions. | J11: 2027-07-31 | K11: Not Started | L11: High | M11: 50 | N11: 0 | O11: System executes timed follow-up sequences across 10 simulated leads, pauses immediately when a reply is detected, and updates CRM status. | P11: Integration tests verifying webhook reply triggers cancellation of future queued follow-up tasks. | Q11: https://github.com/tasim/ai-sales-employee-cadence | S11: Deliverability and spam filtering risks with automated email sequences. | T11: Engineered natural conversational variation and human-like delay intervals between touchpoints.
A12: PRJ-008 | B12: AI Price Negotiation & Quotation Generator Assistant | C12: Custom sales quoting takes hours of manual back-and-forth; sales reps often offer unauthorized discounts or make pricing calculation errors. | D12: Phase 9 | E12: Rule-based business guardrails, PDF document generation, payment gateway integration | F12: Python, ReportLab / WeasyPrint, Jinja2, Stripe API, Pydantic | G12: 1. Strict negotiation logic adhering to maximum allowable discount tiers. 2. Dynamic PDF sales quotation generator with branded layout. 3. Embedded Stripe checkout / deposit payment link. 4. Audit logging of all negotiated concession terms. | H12: PRJ-006, PRJ-007 | I12: 1. Program mathematical discount rules. 2. Design HTML/Jinja2 PDF quote template. 3. Build Stripe payment intent generator. 4. Connect quote generation tool to agent. | J12: 2027-08-15 | K12: Not Started | L12: High | M12: 40 | N12: 0 | O12: Agent negotiates within authorized bounds, produces a clean, professional PDF quote, and emails it to the buyer with an active payment link. | P12: 100 automated adversarial tests confirming the agent never agrees to discounts exceeding business policy. | Q12: https://github.com/tasim/ai-negotiation-quotation-engine | S12: Adversarial prompt injection attacks where buyers convince the LLM to give 90% discounts. | T12: Enforced strict deterministic code-level price validation outside the LLM context.
A13: PRJ-009 | B13: Collaborative Multi-Agent Sales Team | C13: Complex enterprise sales require specialized roles: SDR for prospecting, Solution Engineer for technical Q&A, and Account Executive for closing. | D13: Phase 8 & 9 | E13: Multi-agent coordination, supervisor patterns, LangGraph, CrewAI | F13: Python, LangGraph, CrewAI, ChromaDB, FastAPI | G13: 1. 3 Specialized Autonomous Agents: Prospector Agent, Technical Solution Agent, and Deal Closing Agent. 2. Supervisor router routing customer inquiries to the appropriate agent. 3. Shared conversational memory and handover protocols. | H13: PRJ-004 through PRJ-008 | I13: 1. Define individual agent personas and system prompts. 2. Implement supervisor routing node in LangGraph. 3. Build shared conversation state schema. 4. Run full enterprise sales cycle simulation. | J13: 2027-08-31 | K13: Not Started | L13: Medium | M13: 45 | N13: 0 | O13: Multi-agent team collaboratively handles lead from first touch through technical product inquiry to final contract quotation seamlessly. | P13: End-to-end integration tests measuring token efficiency and inter-agent latency. | Q13: https://github.com/tasim/multi-agent-sales-team | S13: Token explosion and latency compounding across multiple sequential LLM calls. | T13: Optimized state distillation so agents pass concise summaries rather than full conversation histories.
A14: PRJ-010 | B14: Production-Ready AI Sales Platform (Commercial MVP) | C14: Commercial businesses require a secure, multi-tenant, monitored web platform with human-in-the-loop oversight to safely deploy AI sales reps. | D14: Phase 11 & 12 | E14: Full-stack architecture, Docker, FastAPI, PostgreSQL, Redis, Next.js, LangSmith, OWASP Security | F14: Next.js, TypeScript, Tailwind CSS, FastAPI, PostgreSQL (pgvector), Docker, Render/Hetzner, LangSmith | G14: 1. Full multi-tenant web platform with live sales dashboard. 2. Human-in-the-loop approval inbox for high-value quotes and flagged escalations. 3. Conversation transcript viewer with sentiment analysis. 4. Dockerized one-click cloud deployment on Render. 5. Production rate limiting, auth, and OWASP defenses. | H14: All previous projects (PRJ-001 through PRJ-009) | I14: 1. Build FastAPI production backend with JWT auth. 2. Build Next.js operational dashboard. 3. Write Dockerfile & docker-compose stack. 4. Deploy to Render with persistent disk & PostgreSQL. 5. Conduct load test & security audit. | J14: 2027-10-15 | K14: Not Started | L14: High | M14: 70 | N14: 0 | O14: Fully working commercial platform deployed online; handles live chats, executes tool calls, allows human intervention, and logs all metrics reliably. | P14: End-to-end Cypress/Playwright frontend tests, Locust load testing (50 concurrent users), and OWASP security vulnerability scan. | Q14: https://github.com/tasim/autonomous-ai-sales-platform | R14: https://sales-agent-demo.render.com | S14: Cold start latency on cloud hosts and managing API key rate limits under peak load. | T14: Built a commercially viable, standalone AI agent SaaS product ready for customer pilots.
A15: TOTAL ESTIMATED EFFORT (HOURS) | M15: =SUM(M5:M14) | N15: =SUM(N5:N14)

Sheet Daily Study Agenda
A1: 30-DAY DAILY STUDY & EXECUTION AGENDA
A2: Enforced 2–3 Hour Daily Protocol: 45m Concepts • 60m Coding Drills • 60m Project Building • 15m Review & Documentation
A4: Date | B4: Day # | C4: Learning Objective | D4: Planned Activities (Time-Blocked) | E4: Resource Links | F4: Planned Minutes | G4: Actual Minutes | H4: Deliverable | I4: Status | J4: Problems Encountered | K4: Next Action
A5: 2026-11-01 | B5: Day 01 | C5: Python OOP & Type Hinting Discipline | D5: 45m: Review Python 3.11 typing module. 60m: Code custom BaseModel with typing. 60m: Project setup & repo architecture. 15m: Update notes and log difficulties. | E5: RES-017 | F5: 180 | G5: 0 | H5: Git repo with poetry, pytest, typing test cases | I5: Not Started
A6: 2026-11-02 | B6: Day 02 | C6: AsyncIO & Non-blocking Network Calls | D6: 45m: Read AsyncIO event loop docs. 60m: Build async scraper fetching 10 mock pages. 60m: Project: Async CRM client mock. 15m: Reflection and time audit. | E6: RES-017, RES-022 | F6: 180 | G6: 0 | H6: Working async worker script with concurrency benchmark | I6: Not Started
A7: 2026-11-03 | B7: Day 03 | C7: JSON Serialization & Pydantic Validation | D7: 45m: Study Pydantic V2 core concepts. 60m: Code nested data validators. 60m: Project: Lead profile schema validator. 15m: Review and document edge cases. | E7: RES-007, RES-017 | F7: 180 | G7: 0 | H7: Pydantic LeadProfile class with phone/email validation | I7: Not Started
A8: 2026-11-04 | B8: Day 04 | C8: Linear Algebra: Vector Dot Products | D8: 45m: Watch 3Blue1Brown Linear Algebra. 60m: Code vector dot product & norm from scratch. 60m: Compute cosine similarity between 3 text vectors. 15m: Review notes on projections. | E8: RES-018 | F8: 180 | G8: 0 | H8: Python vector math utility file with unit tests | I8: Not Started
A9: 2026-11-05 | B9: Day 05 | C9: Linear Algebra: Matrix Transformations | D9: 45m: Study matrix multiply & transformation geometry. 60m: Write matrix multiply function in pure Python. 60m: Benchmark vs NumPy array operations. 15m: Log lessons learned. | E9: RES-018 | F9: 180 | G9: 0 | H9: Jupyter notebook visualizing 2D matrix shear & rotate | I9: Not Started
A10: 2026-11-06 | B10: Day 06 | C10: Probability: Bayes' Theorem in Sales | D10: 45m: Study conditional probability & Bayes rule. 60m: Write Bayes calculation function. 60m: Project: Model lead conversion odds based on source. 15m: Record quiz questions. | E10: RES-001 | F10: 180 | G10: 0 | H10: Probabilistic lead scoring function with test cases | I10: Not Started
A11: 2026-11-07 | B11: Day 07 | C11: Weekly Review 1 & Rest / Catch-up | D11: 60m: Review Days 1-6 concepts. 60m: Refactor code and commit all repos. 30m: Fill out Weekly Review Worksheet. | E11: Weekly Review Sheet | F11: 150 | G11: 0 | H11: Completed Weekly Review 1 & clean GitHub commits | I11: Not Started
A12: 2026-11-08 | B12: Day 08 | C12: Calculus: Derivatives & Loss Functions | D12: 45m: Derivatives, gradients, and partial derivatives. 60m: Code manual derivative calculation. 60m: Implement Mean Squared Error (MSE) loss function. 15m: Summary. | E12: RES-001 | F12: 180 | G12: 0 | H12: Python notebook calculating analytic & numerical gradients | I12: Not Started
A13: 2026-11-09 | B13: Day 09 | C13: Optimization: Gradient Descent from Scratch | D13: 45m: Study batch vs stochastic gradient descent. 60m: Write gradient descent loop finding minimum. 60m: Plot descent trajectory across learning rates. 15m: Document overshoot risks. | E13: RES-001 | F13: 180 | G13: 0 | H13: Working 2D gradient descent optimizer visualization | I13: Not Started
A14: 2026-11-10 | B14: Day 10 | C14: NumPy Vectorization & Broadcasting | D14: 45m: Study NumPy memory layout and broadcasting rules. 60m: Solve 15 array manipulation exercises. 60m: Vectorize sales transaction table processing. 15m: Log performance stats. | E14: RES-018 | F14: 180 | G14: 0 | H14: Benchmarked NumPy vectorized functions vs Python loops | I14: Not Started
A15: 2026-11-11 | B15: Day 11 | C15: Pandas DataFrames: Filtering & Aggregation | D15: 45m: Read Pandas user guide on indexing and groupby. 60m: Perform complex queries on 10k sales records. 60m: Calculate monthly sales velocity by segment. 15m: Note syntax gotchas. | E15: RES-019 | F15: 180 | G15: 0 | H15: Pandas data wrangling script producing cohort summary | I15: Not Started
A16: 2026-11-12 | B16: Day 12 | C16: Exploratory Data Analysis: Outliers & Missing Values | D16: 45m: Study data hygiene and imputation strategies. 60m: Write automated missing data detection script. 60m: Impute median values and flag anomalies. 15m: Document data leakage traps. | E16: RES-002, RES-019 | F16: 180 | G16: 0 | H16: Reusable data cleaning function with logging | I16: Not Started
... A34: 2026-11-30 | B34: Day 30 | C34: Month 1 Retrospective & Phase 3 Transition Plan | D34: 60m: Audit total hours logged vs 75h target. 60m: Refactor codebases and organize notes. 45m: Finalize Phase 3 Deep Learning study schedule. 15m: Month 1 completion sign-off. | E34: Dashboard Sheet | F34: 180 | G34: 0 | H34: Month 1 retrospective document & Phase 3 roadmap | I34: Not Started
A35: TOTAL PLANNED MINUTES (30 DAYS) | F35: =SUM(F5:F34) | G35: =SUM(G5:G34)

Sheet Weekly Review and Analysis
A1: WEEKLY LEARNING RETROSPECTIVE & GAP ANALYSIS
A2: 12-Week Honest Performance Review: Measuring Study Discipline, Weak Concepts, Inefficiencies, and Actionable Adjustments
A4: Week Starting | B4: Week # | C4: Planned Hours | D4: Actual Hours | E4: Topics Planned | F4: Topics Completed | G4: Exercises Done | H4: Projects Advanced | I4: Assessment Avg (%) | J4: Skills Improved | K4: Strongest Topics | L4: Weakest Topics | M4: Blockers Encountered | N4: Time Wasted / Inefficiencies | O4: Key Lessons Learned | P4: Next Week Goals & Schedule Adjustments | Q4: Overall Confidence (1-5)
A5: 2026-11-01 | B5: Week 01 | C5: 16 | D5: 0 | E5: 5 | F5: 0 | G5: Async HTTP client, Vector dot products | H5: Dev environment setup & testing suite | J5: Python type hints, matrix geometry | K5: Python OOP, basic algebra | L5: Eigenvalues, async event loops | M5: None | N5: Spent 1.5h tweaking VS Code themes instead of coding | O5: Write tests before implementing business logic. | P5: Master gradient descent and start Pandas. | Q5: 3
A6: 2026-11-08 | B6: Week 02 | C6: 17.5 | D6: 0 | E6: 5 | F6: 0 | G6: Gradient descent loop, NumPy matrix drills | H6: Scratch math repository | J6: Optimization math, vectorized arrays | K6: Gradient descent intuition | L6: Partial derivatives chain rule | M6: Math notation confusion | N6: Passive reading of math blogs without writing formulas by hand | O6: Work through calculus examples on paper first. | P6: Deep dive into Pandas data wrangling. | Q6: 3
A7: 2026-11-15 | B7: Week 03 | C7: 16 | D7: 0 | E7: 4 | F7: 0 | G7: Pandas aggregation, data cleaning scripts | H7: Project 1: Sales Data Analysis | J7: Data hygiene, outlier detection | K7: Pandas filtering, Matplotlib heatmaps | L7: Datetime parsing edge cases | M7: Dirty CSV date formats | N7: Overcomplicating data visualization layout | O7: Vectorized Pandas operations are 100x faster than loops. | P7: Complete Project 1 executive report. | Q7: 4
A8: 2026-11-22 | B8: Week 04 | C8: 18 | D8: 0 | E8: 5 | F8: 0 | G8: RFM segmentation, Logistic Regression scratch | H8: Project 1 & Project 2 setup | J8: RFM customer segmentation, Scikit-learn | K8: Classification intuition | L8: Log-odds mathematical interpretation | M8: Missing CRM values | N8: Debugging Scikit-Learn pipeline column types | O8: Always check feature types with df.info() before fitting. | P8: Train XGBoost model for customer prediction. | Q8: 3
A9: 2026-11-29 | B9: Week 05 | C9: 16 | D9: 0 | E9: 4 | F9: 0 | G9: Decision trees, Random Forest, XGBoost | H9: Project 2: Customer Purchase Predictor | J9: Tree ensembles, ROC-AUC evaluation | K9: Feature importance interpretation | L9: Class imbalance hyperparameter tuning | M9: High class imbalance (97% negative) | N9: Searching StackOverflow blindly instead of reading docs | O9: Use Precision-Recall curve when classes are highly skewed. | P9: Complete Project 2 GitHub submission. | Q9: 4
A10: 2026-12-06 | B10: Week 06 | C10: 17 | D10: 0 | E10: 4 | F10: 0 | G10: K-Means clustering, PCA dimensionality reduction | H10: Project 2 tuning & Project 3 setup | J10: Unsupervised learning, clustering | K10: K-Means elbow method | L10: PCA variance interpretation | M10: Sparse feature matrices | N10: Spent 2 hours rewriting working clustering algorithm | O10: Start with Scikit-learn baseline before writing custom code. | P10: Begin PyTorch deep learning blitz. | Q10: 3
A11: 2026-12-13 | B11: Week 07 | C11: 18 | D11: 0 | E11: 4 | F11: 0 | G11: PyTorch tensors, autograd backwards pass | H11: Project 3: Intent Classifier | J11: PyTorch tensor operations, CUDA setup | K11: Autograd computation graphs | L11: Tensor dimension broadcasting rules | M11: CUDA out-of-memory errors on GPU | N11: Debugging shape mismatch errors without printing tensor.shape | O11: Always write assert tensor.shape == (B, C, H, W) before operations. | P11: Train multi-layer perceptron in PyTorch. | Q11: 3
A12: 2026-12-20 | B12: Week 08 | C12: 16.5 | D12: 0 | E12: 4 | F12: 0 | G12: PyTorch MLP, custom Dataset, AdamW optimizer | H12: Project 3: Intent Classifier | J12: Neural network training loops, early stopping | K12: Loss function selection | L12: Learning rate scheduling | M12: Overfitting on small training set | N12: Letting model train 50 epochs after validation loss plateaus | O12: Implement early stopping based on validation loss. | P12: Tokenization and Transformer attention mechanism. | Q12: 4
A13: 2026-12-27 | B13: Week 09 | C13: 16 | D13: 0 | E13: 3 | F13: 0 | G13: BPE tokenization, self-attention PyTorch module | H13: Transformer scratch notebook | J13: Scaled dot-product attention math | K13: Tokenization economics, tiktoken | L13: Multi-head attention tensor reshaping | M13: Causal attention masking logic | N13: Struggled with matrix dimensions in attention layer | O13: Self-attention is simply a weighted average of values by query-key similarity. | P13: Prompt engineering and structured outputs. | Q13: 4
A14: 2027-01-03 | B14: Week 10 | C14: 17 | D14: 0 | E14: 4 | F14: 0 | G14: Pydantic structured output, OpenAI API wrapper | H14: BANT extraction pipeline | J14: Constrained JSON decoding, prompt defense | K14: Deterministic schema extraction | L14: Rate limit exponential backoffs | M14: API 429 rate limit exceptions | N14: Writing complex regex parsers instead of using native structured outputs | O14: Use official response_format=json_schema; never parse JSON with regex. | P14: Embeddings, vector databases, and RAG. | Q14: 4
A15: 2027-01-10 | B15: Week 11 | C15: 18 | D15: 0 | E15: 4 | F15: 0 | G15: pgvector setup, semantic chunking pipeline | H15: Project 4: Product Knowledge Assistant | J15: Vector indexing, cosine search, hybrid retrieval | K15: pgvector SQL integration | L15: BM25 keyword search tuning | M15: Chunking table data in PDF documents | N15: Trying to chunk PDFs without extracting markdown structure | O15: Clean markdown conversion is 80% of RAG retrieval success. | P15: AI Agent tool calling and LangGraph state loops. | Q15: 4
A16: 2027-01-17 | B16: Week 12 | C16: 18 | D16: 0 | E16: 4 | F16: 0 | G16: ReAct agent loop, tool execution dispatcher | H16: Project 5 & Project 6 setup | J16: Agent reasoning loops, tool calling schemas | K16: Function calling with Pydantic | L16: Handling tool execution failure gracefully | M16: LLM hallucinating tool arguments | N16: Vague tool docstrings causing LLM confusion | O16: Tool parameter docstrings must be as clear and precise as human API documentation. | P16: Build multi-agent sales qualification workflow. | Q16: 4
A17: TOTAL PLANNED HOURS | C17: =SUM(C5:C16) | D17: =SUM(D5:D16)

Sheet Progress Dashboard
A1: EXECUTIVE AI LEARNING & PROJECT PERFORMANCE DASHBOARD
A2: Automated Real-Time Analytics Powered by Dynamic Formulas Connecting All 12 Curricula and Projects
A4: 1. STRATEGIC METRICS & LEARNING PROGRESS KPIS
A5: TOTAL TOPICS | C5: COMPLETED TOPICS | E5: TOPICS IN PROGRESS | G5: BLOCKED TOPICS | I5: OVERALL COMPLETION %
A6: =COUNTA('Topic Completion Checklist'!C5:C56) | C6: =COUNTIF('Topic Completion Checklist'!G5:G56, "Completed") + COUNTIF('Topic Completion Checklist'!G5:G56, "Mastered") | E6: =COUNTIF('Topic Completion Checklist'!G5:G56, "In Progress") | G6: =COUNTIF('Topic Completion Checklist'!G5:G56, "Blocked") | I6: =IF(A6>0, C6/A6, 0)
A8: PLANNED STUDY HOURS | C8: ACTUAL STUDY HOURS | E8: PROJECTS COMPLETED | G8: TUTORIALS COMPLETED | I8: AVG CONFIDENCE (1-5)
A9: =SUM('Master Roadmap'!H5:H16) | C9: =SUM('Master Roadmap'!I5:I16) | E9: =COUNTIF('AI Project Backlog'!K5:K14, "Completed") | G9: =COUNTIF('Tutorial and Course Tracker'!L5:L20, "Completed") | I9: =AVERAGE('Topic Completion Checklist'!H5:H56)
A12: 2. 12-PHASE ROADMAP EXECUTION & HOUR TRACKING
A13: Phase # | B13: Phase Name | C13: Planned Hours | D13: Actual Hours | E13: Status | F13: Progress %
A14: Phase 1 | B14: ='Master Roadmap'!B5 | C14: ='Master Roadmap'!H5 | D14: ='Master Roadmap'!I5 | E14: ='Master Roadmap'!N5 | F14: =IF(C14>0, D14/C14, 0)
A15: Phase 2 | B15: ='Master Roadmap'!B6 | C15: ='Master Roadmap'!H6 | D15: ='Master Roadmap'!I6 | E15: ='Master Roadmap'!N6 | F15: =IF(C15>0, D15/C15, 0)
A16: Phase 3 | B16: ='Master Roadmap'!B7 | C16: ='Master Roadmap'!H7 | D16: ='Master Roadmap'!I7 | E16: ='Master Roadmap'!N7 | F16: =IF(C16>0, D16/C16, 0)
A17: Phase 4 | B17: ='Master Roadmap'!B8 | C17: ='Master Roadmap'!H8 | D17: ='Master Roadmap'!I8 | E17: ='Master Roadmap'!N8 | F17: =IF(C17>0, D17/C17, 0)
A18: Phase 5 | B18: ='Master Roadmap'!B9 | C18: ='Master Roadmap'!H9 | D18: ='Master Roadmap'!I9 | E18: ='Master Roadmap'!N9 | F18: =IF(C18>0, D18/C18, 0)
A19: Phase 6 | B19: ='Master Roadmap'!B10 | C19: ='Master Roadmap'!H10 | D19: ='Master Roadmap'!I10 | E19: ='Master Roadmap'!N10 | F19: =IF(C19>0, D19/C19, 0)
A20: Phase 7 | B20: ='Master Roadmap'!B11 | C20: ='Master Roadmap'!H11 | D20: ='Master Roadmap'!I11 | E20: ='Master Roadmap'!N11 | F20: =IF(C20>0, D20/C20, 0)
A21: Phase 8 | B21: ='Master Roadmap'!B12 | C21: ='Master Roadmap'!H12 | D21: ='Master Roadmap'!I12 | E21: ='Master Roadmap'!N12 | F21: =IF(C21>0, D21/C21, 0)
A22: Phase 9 | B22: ='Master Roadmap'!B13 | C22: ='Master Roadmap'!H13 | D22: ='Master Roadmap'!I13 | E22: ='Master Roadmap'!N13 | F22: =IF(C22>0, D22/C22, 0)
A23: Phase 10 | B23: ='Master Roadmap'!B14 | C23: ='Master Roadmap'!H14 | D23: ='Master Roadmap'!I14 | E23: ='Master Roadmap'!N14 | F23: =IF(C23>0, D23/C23, 0)
A24: Phase 11 | B24: ='Master Roadmap'!B15 | C24: ='Master Roadmap'!H15 | D24: ='Master Roadmap'!I15 | E24: ='Master Roadmap'!N15 | F24: =IF(C24>0, D24/C24, 0)
A25: Phase 12 | B25: ='Master Roadmap'!B16 | C25: ='Master Roadmap'!H16 | D25: ='Master Roadmap'!I16 | E25: ='Master Roadmap'!N16 | F25: =IF(C25>0, D25/C25, 0)
A26: TOTAL ROADMAP HOURS | C26: =SUM(C14:C25) | D26: =SUM(D14:D25) | E26: - | F26: =IF(C26>0, D26/C26, 0)

Sheet Notes and Document Library
A1: KNOWLEDGE BASE & TECHNICAL DOCUMENT LIBRARY
A2: Structured Index of Architecture Blueprints, Research Paper Notes, Code Snippets, and Technical Reference Documents
A4: Document ID | B4: Date | C4: Topic | D4: Document Type | E4: Title | F4: Local File Path | G4: URL / Reference | H4: Summary | I4: Key Concepts | J4: Code Examples / Snippets | K4: Related Project | L4: Questions to Research | M4: Next Review Date
A5: DOC-001 | B5: 2026-11-04 | C5: Python / Architecture | D5: Architecture Decision | E5: Pydantic V2 State Representation Pattern for Agents | F5: docs/architecture/adr_001_pydantic_state.md | G5: https://docs.pydantic.dev/latest/ | H5: Standardized protocol for agent state dictionaries using typed Pydantic models with field validation. | I5: Immutable state snapshots, TypeAdapter, Field constraints, model_dump(mode='json'). | J5: class AgentState(BaseModel): messages: list[ChatMessage] bant_score: int = Field(ge=0, le=100) current_step: str | K5: PRJ-005, PRJ-006 | L5: Performance difference between Pydantic validation and raw TypedDict in high-throughput loops? | M5: 2026-12-01
A6: DOC-002 | B6: 2026-11-10 | C6: Mathematics | D6: Cheat Sheet | E6: Vector Math & Dot Product Formulas for AI Engineers | F6: notes/math/vector_math_cheatsheet.md | G6: https://3blue1brown.com | H6: Complete mathematical formulas for Euclidean distance, Dot Product, Cosine Similarity, and Matrix Transpose. | I6: u . v = ||u|| ||v|| cos(theta); Cosine similarity range [-1, 1]; L2 normalization. | J6: def cosine_sim(a, b): return np.dot(a, b) / (np.linalg.norm(a) * np.linalg.norm(b)) | K6: PRJ-004 | L6: How does floating point rounding error affect cosine similarity on 1536-dimensional vectors? | M6: 2026-12-15
A7: DOC-003 | B7: 2026-12-15 | C7: Machine Learning | D7: Experiment Report | E7: Class Imbalance Handling Strategies in B2B Lead Conversion | F7: experiments/reports/imbalance_lead_conversion.md | G7: https://scikit-learn.org | H7: Empirical comparison of SMOTE oversampling vs Balanced Random Forest vs class_weight='balanced'. | I7: Precision-recall trade-off; Cost-sensitive matrix: Missing a $10k deal costs 50x more than an unnecessary sales call. | J7: clf = RandomForestClassifier(class_weight={0: 1, 1: 25}, random_state=42) | K7: PRJ-002 | L7: What is the optimal classification threshold when sales rep capacity is limited to 20 calls/day? | M7: 2027-01-10
A8: DOC-004 | B8: 2027-01-20 | C8: Deep Learning | D8: Paper Summary | E8: Summary: Attention Is All You Need (Vaswani et al. 2017) | F8: notes/papers/attention_is_all_you_need_summary.md | G8: https://arxiv.org/abs/1706.03762 | H8: Deconstruction of self-attention mechanisms, multi-head attention, positional encoding, and layer normalization. | I8: Queries, Keys, Values; Scaled dot product avoids vanishing gradients when d_k is large; Parallel training vs RNN sequential bottleneck. | J8: def attention(q, k, v, mask=None): scores = (q @ k.transpose(-2, -1)) / math.sqrt(q.size(-1)) if mask: scores.masked_fill_(mask == 0, -1e9) return F.softmax(scores, dim=-1) @ v | K8: PRJ-003 | L8: Why did modern LLMs switch from Post-LN (original paper) to Pre-LN or RMSNorm? | M8: 2027-02-15
A9: DOC-005 | B9: 2027-03-05 | C9: Prompting | D9: Code Snippet | E9: Production Structured Output Extraction with OpenAI SDK | F9: snippets/llm/structured_output_helper.py | G9: https://platform.openai.com/docs/guides/structured-outputs | H9: Production-ready wrapper enforcing strict JSON schema adherence with automatic Pydantic parsing. | I9: response_format=PydanticModel, strict=True, system message conditioning, temperature=0.0 for zero extraction variance. | J9: completion = client.beta.chat.completions.parse( model='gpt-4o-mini', messages=[{'role': 'user', 'content': text}], response_format=BANTLeadScore ) | K9: PRJ-005, PRJ-006 | L9: What is the token overhead of OpenAI's strict JSON schema constrained decoding? | M9: 2027-04-01
A10: DOC-006 | B10: 2027-04-15 | C10: RAG | D10: Architecture Decision | E10: Enterprise Hybrid Search Architecture with PostgreSQL pgvector | F10: docs/architecture/adr_002_pgvector_hybrid_search.md | G10: https://github.com/pgvector/pgvector | H10: Combining PostgreSQL full-text search (tsvector/BM25) with dense vector HNSW cosine similarity in a single query. | I10: Reciprocal Rank Fusion (RRF), HNSW indexing parameters (m=16, ef_construction=64), single-database operational simplicity. | J10: SELECT id, content, (0.7 * (1 - (embedding <=> query_vector)) + 0.3 * ts_rank_cd(textsearch, query)) AS score FROM product_docs ORDER BY score DESC LIMIT 5; | K10: PRJ-004 | L10: How often must HNSW index be rebuilt when adding 1,000 new product catalog rows per day? | M10: 2027-05-01
A11: DOC-007 | B11: 2027-05-15 | C11: AI Agents | D11: Cheat Sheet | E11: ReAct Loop Pattern: State Machine vs Free-Form Loop | F11: notes/agents/react_loop_patterns.md | G11: https://langchain-ai.github.io/langgraph/ | H11: Comparison of unconstrained while-loop ReAct vs deterministic state machine graphs for business automation. | I11: Deterministic State Graphs prevent infinite loops, enable persistent checkpoints, and simplify human-in-the-loop gates. | J11: workflow = StateGraph(SalesState) workflow.add_node('qualify', qualify_node) workflow.add_conditional_edges('qualify', route_lead) | K11: PRJ-006, PRJ-007 | L11: How to dynamically inject user interruptions into an active agent multi-tool reasoning sequence? | M11: 2027-06-01
A12: DOC-008 | B12: 2027-06-20 | C12: AI Agents | D12: Architecture Decision | E12: Autonomous Negotiation Guardrails & Concession Curves | F12: docs/architecture/adr_003_negotiation_guardrails.md | G12: https://github.com/tasim/sales-agent | H12: Strict deterministic rules preventing autonomous AI sales reps from violating pricing floors. | I12: Hard concession ceilings (max 15% discount), margin validation, manager approval interrupts, audit trail logging. | J12: def calculate_discount(margin, requested): if requested > 0.15: return trigger_human_review() return min(requested, margin * 0.4) | K12: PRJ-008 | L12: What fallback copy should the agent say when customer insists on a 25% discount? | M12: 2027-07-15
A13: DOC-009 | B13: 2027-08-25 | C13: Fine-Tuning | D13: Experiment Report | E13: LoRA Rank (r) & Alpha Optimization for Objection Handling | F13: experiments/reports/lora_rank_hyperparameters.md | G13: https://github.com/unslothai/unsloth | H13: Benchmarked r=8, r=16, r=32 across 300 sales objection training pairs on Llama-3-8B. | I13: r=16 with alpha=32 provided optimal balance of style adaptation and zero catastrophic forgetting of factual knowledge. | J13: peft_config = LoraConfig(r=16, lora_alpha=32, target_modules=['q_proj', 'k_proj', 'v_proj', 'o_proj']) | K13: PRJ-009 | L13: Does QLoRA 4-bit quantization affect conversational nuance in consultative sales? | M13: 2027-09-15
A14: DOC-010 | B14: 2027-09-25 | C14: Production | D14: Cheat Sheet | E14: OWASP Top 10 for LLMs: Defensive Implementation Checklist | F14: notes/security/owasp_llm_defenses.md | G14: https://owasp.org | H14: Tactical defensive rules: System prompt boundary tags, tool parameter regex sanitization, output guardrails. | I14: LLM01 Prompt Injection, LLM02 Insecure Output, LLM06 Excessive Agency, LLM08 Denial of Service. | J14: def sanitize_input(user_prompt: str) -> str: if any(w in user_prompt.lower() for w in ['ignore previous instructions', 'system override']): raise SecurityException('Suspicious prompt pattern detected') | K14: PRJ-010 | L14: How to defend against indirect prompt injection hidden inside customer-submitted website links? | M14: 2027-10-15

Sheet AI Experiment Log
A1: SCIENTIFIC AI EXPERIMENT & BENCHMARK LOG
A2: Rigorous Measurement of Prompts, Hyperparameters, Latency, Token Costs, Tool Calling Accuracy & Failure Modes
A4: Experiment ID | B4: Date | C4: Research Question / Hypothesis | D4: Model / Provider | E4: Model Version | F4: Dataset / Test Suite | G4: Prompt / Config Version | H4: Parameters | I4: Evaluation Benchmark | J4: Primary Metric | K4: Latency (ms) | L4: Cost / Run ($) | M4: Compute / VRAM | N4: Failure Cases Observed | O4: Comparison Baseline | P4: Conclusion & Key Takeaway | Q4: Next Experiment & Link
A5: EXP-001 | B5: 2026-12-18 | C5: Does XGBoost with tuned hyperparams outperform Random Forest on B2B lead conversion? | D5: XGBoost vs Scikit-Learn RF | E5: xgboost v2.0.3, sklearn v1.4 | F5: 10,000 anonymized SaaS CRM records | G5: v1.0 (5-fold stratified CV) | H5: n_estimators=300, max_depth=5, lr=0.05, subsample=0.8 | I5: Held-out test set (2,000 records) | J5: ROC-AUC: 0.864 vs 0.821 | K5: 145 ms (inference 100 rows) | L5: $0.00 | M5: CPU 4 cores, 1.2 GB RAM | N5: Slight drop in recall on newly founded startups (< 6 months operating history). | O5: Scikit-Learn baseline RandomForest (AUC: 0.821) | P5: XGBoost improved ROC-AUC by 4.3 percentage points and inference was 2.5x faster. | Q5: EXP-002: Add interaction terms between website visits and company headcount.
A6: EXP-002 | B6: 2027-01-22 | C6: Can PyTorch MLP match XGBoost accuracy on tabular CRM data with learned categorical embeddings? | D6: PyTorch Tabular MLP | E6: PyTorch 2.2 CUDA 12.1 | F6: 10,000 SaaS CRM records with 4 categorical features | G6: TabularNet v1.2 | H6: Embedding dim=16, 2 hidden layers (128, 64), AdamW lr=1e-3, batch=64 | I6: Held-out test set (2,000 records) | J6: ROC-AUC: 0.835 vs 0.864 | K6: 85 ms (GPU batch) | L6: $0.00 | M6: GPU RTX 3080, 800 MB VRAM | N6: Overfits faster than tree ensembles on sparse industry categories with low sample count. | O6: XGBoost baseline from EXP-001 (AUC: 0.864) | P6: XGBoost remains superior on purely tabular CRM data; deep learning requires 10x more data. | Q6: EXP-003: Focus deep learning on text message intent classification where it excels.
A7: EXP-003 | B7: 2027-03-05 | C7: Does OpenAI native Structured Outputs eliminate malformed JSON errors compared to zero-shot prompting? | D7: OpenAI GPT-4o-mini | E7: gpt-4o-mini-2024-07-18 | F7: 100 complex, messy sales call transcripts | G7: Prompt v2.1 with Pydantic BANT schema | H7: temperature=0.0, response_format=PydanticModel, max_tokens=1000 | I7: 100 transcript test suite | J7: Schema Validity: 100% vs 87% | K7: 820 ms avg | L7: $0.00042 / call | M7: Cloud API | N7: Zero schema failures with native structured outputs. Zero-shot baseline failed on nested arrays. | O7: Zero-shot prompting with markdown ```json codeblocks | P7: Native Structured Outputs guarantees 100% schema compliance and completely eliminates retry loops. | Q7: EXP-004: Test extraction latency and cost between GPT-4o-mini and Gemini-1.5-Flash.
A8: EXP-004 | B8: 2027-03-12 | C8: Cost & Latency comparison: GPT-4o-mini vs Gemini-1.5-Flash for real-time lead qualification. | D8: GPT-4o-mini vs Gemini-1.5-Flash | E8: gpt-4o-mini vs gemini-1.5-flash-001 | F8: 50 customer chat dialogue transcripts | G8: Standardized qualification prompt v3.0 | H8: temp=0.0, strict structured JSON output mode | I8: 50 multi-turn test dialogues | J8: F1 on BANT extraction: 0.92 vs 0.90 | K8: GPT-4o-mini: 680ms | Gemini: 420ms | L8: GPT: $0.00038 | Gemini: $0.00018 | M8: Cloud API | N8: Gemini-1.5-Flash was occasionally too conservative on extracting numeric budget values. | O8: GPT-4o-mini baseline | P8: Gemini-1.5-Flash is 38% faster and 52% cheaper, making it the ideal choice for high-volume chat webhooks. | Q8: EXP-005: Benchmark RAG chunk sizes for product catalog retrieval.
A9: EXP-005 | B9: 2027-04-10 | C9: What is the optimal chunk size (256 vs 512 vs 1024 tokens) for product specification retrieval? | D9: OpenAI text-embedding-3-small + pgvector | E9: text-embedding-3-small, dim=1536 | F9: 150-page enterprise software catalog & pricing sheets | G9: RecursiveCharacterTextSplitter with overlap=10% | H9: Cosine similarity, top_k=5 retrieval | I9: 50 synthetic product domain queries | J9: Recall@5: 256t: 74% | 512t: 91% | 1024t: 82% | K9: 18 ms (PostgreSQL pgvector query) | L9: $0.00002 / query | M9: Local PostgreSQL container, 500 MB RAM | N9: 256-token chunks fragmented pricing tables; 1024-token chunks diluted specific SKU keyword relevance. | O9: Naive 1000-character fixed chunking (Recall@5: 68%) | P9: 512-token chunking with 50-token overlap yielded the highest retrieval accuracy (91% Recall@5). | Q9: EXP-006: Add BM25 hybrid search and cross-encoder reranking to 512-token chunks.
A10: EXP-006 | B10: 2027-04-18 | C10: Does Cross-Encoder reranking improve RAG retrieval accuracy on exact product part numbers? | D10: Cohere Rerank v3 vs Dense Cosine | E10: cohere/rerank-v3.5 + text-embedding-3-small | F10: Software catalog with 40 specific part numbers/SKUs | G10: Hybrid retrieval pipeline v2.0 | H10: top_k_retrieve=20, top_n_rerank=5 | I10: 40 exact SKU and part number queries | J10: Top-1 Accuracy: 95% vs 72% | K10: 120 ms (Dense: 22ms + Rerank: 98ms) | L10: $0.0012 / query | M10: API / Local container | N10: Minor latency increase (+98ms), well within interactive chat tolerance (< 1.5s). | O10: Dense vector search alone (72% Top-1 Accuracy) | P10: Cross-Encoder reranking drastically improves retrieval on specific technical terms and part numbers. | Q10: EXP-007: Test tool calling reliability of Llama-3-8B locally vs GPT-4o-mini.
A11: EXP-007 | B11: 2027-05-18 | C11: Can local Llama-3-8B-Instruct reliably call 4 business tools without argument hallucination? | D11: Meta Llama-3-8B-Instruct (4-bit) | E11: Llama-3-8B-Instruct-GGUF (Q4_K_M) via Ollama | F11: 50 multi-step tool execution scenarios | G11: ReAct tool prompt with JSON schema definitions | H11: temperature=0.1, max_tokens=512, top_p=0.9 | I11: 50 simulated tool-use test tasks | J11: Tool Call Accuracy: 84% vs 98% (GPT-4o-mini) | K11: 1,450 ms (local RTX 3080) | L11: $0.00 (Self-hosted) | M11: 6.2 GB VRAM on GPU | N11: Llama-3-8B sometimes hallucinated optional parameters or invoked non-existent tools when confused. | O11: GPT-4o-mini tool execution accuracy (98%) | P11: Llama-3-8B is viable for single-tool tasks, but multi-tool agentic planning still requires frontier APIs. | Q11: EXP-008: Test system prompt defenses against adversarial discount extraction attacks.
A12: EXP-008 | B12: 2027-08-10 | C12: Can adversarial prompt injection bypass autonomous sales agent pricing guardrails? | D12: GPT-4o-mini with NeMo Guardrails | E12: gpt-4o-mini + NeMo Guardrails v0.8 | F12: 30 adversarial jailbreak prompts ('Forget previous instructions', etc.) | G12: System prompt v4.0 with deterministic code guardrails | H12: temperature=0.0, code-level price floor validator | I12: 30 adversarial prompt attack suite | J12: Jailbreak Defense Rate: 100% | K12: 710 ms avg | L12: $0.00045 / test | M12: Cloud API + local validator | N12: LLM was tricked twice by clever roleplay, BUT deterministic code layer caught and blocked the discount. | O12: Prompt-only defense (failed 6 out of 30 attacks; 80% defense rate) | P12: NEVER rely solely on prompt instructions for business security. Always enforce hard code-level bounds. | Q12: Next: Deploy production platform with deterministic audit logger.

Sheet Commercial Product Validation
A1: COMMERCIAL PRODUCT & MARKET VALIDATION TRACKER
A2: Customer Discovery, Willingness to Pay, Unit Economics & Pilot Verification for Autonomous Commercial AI Employees
A4: Opportunity ID | B4: Product / Agent Concept | C4: Target Industry | D4: Customer Segment | E4: Customer Core Problem | F4: Existing Manual Workflow | G4: Current Cost / Hours | H4: Proposed Autonomous AI Solution | I4: Interview Date | J4: Customer Feedback Summary | K4: Willingness to Pay ($/mo) | L4: Competitors & Alternatives | M4: Technical Feasibility | N4: Integration Requirements | O4: Est. Operating Cost ($/mo) | P4: Expected Business ROI | Q4: Validation Status | R4: Next Action
A5: VAL-001 | B5: Autonomous Inbound SDR for B2B SaaS | C5: B2B SaaS / Tech Startups | D5: Mid-market sales directors & founders (10-50 employees) | E5: Leads who sign up on website wait 4-24 hours for follow-up; 50% drop off to competitors. | F5: Junior SDRs manually review form submissions, research company on LinkedIn, and send template emails. | G5: $4,500/mo salary per junior SDR + $500/mo tooling; 35 hours/week spent on manual qualification. | H5: Autonomous AI Sales Employee that responds within 60 seconds, qualifies via interactive chat/email, and books demos directly on rep calendars. | I5: 2027-02-15 | J5: Founders enthusiastic about sub-minute response time; primary concern is AI hallucinating features or making commitments. | K5: $499 - $1,200 / month | L5: Drift, Qualified, Intercom Fin, human SDR agencies | M5: High | N5: HubSpot CRM, Google Calendar, Slack webhooks, SendGrid | O5: $25 - $45 / month (tokens & cloud) | P5: 3x increase in qualified demo bookings; pays for itself within first closed customer. | Q5: Solution Validated | R5: Build working interactive prototype for 3 pilot SaaS companies.
A6: VAL-002 | B6: Real Estate WhatsApp Inbound Qualifier & Booking Agent | C6: Real Estate Agencies | D6: Independent brokerage owners & top-producing real estate agents | E6: Brokers receive 100+ WhatsApp inquiries daily from portal listings; 70% are unqualified browsers, wasting hours of agent time. | F6: Agents manually reply to each WhatsApp message, ask budget/location questions, and send PDF brochures. | G6: $2,500/mo admin assistant salary; agents lose high-value buyers while chatting with unqualified renters. | H6: WhatsApp AI Sales Concierge that engages immediately, verifies buyer pre-approval & budget, shares matching listings, and schedules property viewings. | I6: 2027-04-10 | J6: Brokers love WhatsApp integration; must strictly avoid answering legal/title questions and hand off to licensed agents. | K6: $299 - $600 / month + $10/booked tour | L6: ManyChat, standard WhatsApp bots, human VAs | M6: High | N6: Meta WhatsApp Cloud API, Property MLS database / Airtable, Google Calendar | O6: $30 - $60 / month | P6: Saves 25 agent hours weekly and ensures zero missed leads on weekends and evenings. | Q6: Problem Confirmed | R6: Connect LangGraph agent to WhatsApp sandbox with sample property catalog.
A7: VAL-003 | B7: Solar & Home Services Appointment Setting Agent | C7: Residential Solar & HVAC | D7: Operations managers & sales leaders at residential solar contractors | E7: Homeowners request quotes online but ignore phone calls; cost per lead is $150+, and uncontacted leads burn marketing spend. | F7: Call center reps dial leads 5-8 times across 2 weeks; average contact rate is under 18%. | G7: $30,000/mo call center overhead; $150 customer acquisition cost per raw uncontacted lead. | H7: Omnichannel AI agent initiating instant SMS/WhatsApp and email follow-up sequence, calculating roof solar viability via RAG, and booking on-site consultations. | I7: 2027-06-05 | J7: Extreme urgency: lead acquisition costs are rising; converting 5% more leads doubles net profitability. | K7: $800 - $2,000 / month (or $50 / completed appointment) | L7: Podium, Verse.io, offshore call centers | M7: High | N7: Twilio SMS, Google Maps API, Jobber / ServiceTitan CRM | O7: $50 - $90 / month | P7: Increases lead contact rate from 18% to 45%; 200%+ ROI in month 1. | Q7: Customer Interviewed | R7: Draft technical scope integrating Google Solar API with WhatsApp agent.
A8: VAL-004 | B8: E-Commerce Cart Abandonment & Negotiation Concierge | C8: Direct-to-Consumer (DTC) E-Commerce | D8: E-commerce brand owners with average order value (AOV) > $150 | E8: Shoppers abandon carts on high-ticket items ($200-$1,000) due to shipping costs, product questions, or indecision. | F8: Generic automated 10% discount email sequence sent 24 hours later; low engagement rate (8-12%). | G8: Loss of $50,000+ in abandoned cart revenue monthly for average store. | H8: AI Sales Employee reaching out via SMS/WhatsApp within 15 minutes, answering product sizing/compatibility questions, and offering dynamic authorized discounts. | I8: 2027-07-12 | J8: E-commerce owners want tight guardrails on discounts and easy Shopify App Store installation. | K8: $399 / month + 3% revenue share on recovered sales | L8: Klaviyo SMS, Gorgias, Cartloop | M8: Medium | N8: Shopify API, Klaviyo, WhatsApp / Twilio SMS | O8: $40 - $70 / month | P8: Recovers an extra $8,000 - $15,000 in monthly sales with zero staff intervention. | Q8: Idea | R8: Build Shopify mock webhook listening for `carts/create` event.
A9: VAL-005 | B9: IT Services Scope & Proposal Drafting Agent | C9: B2B IT & Software Agencies | D9: Agency founders & technical account executives (5-30 developers) | E9: Scoping customer custom software requests and drafting formal 15-page PDF proposals takes 10-15 hours per lead. | F9: Senior engineers and founders spend weekend hours writing scope documents, deliverables lists, and rate cards. | G9: $150/hr senior engineering opportunity cost; $1,500+ cost per proposal drafted. | H9: AI Sales Engineer that analyzes client requirements transcripts, drafts complete technical specification, line-item pricing, and generates branded PDF quote. | I9: 2027-08-20 | J9: Agencies excited about saving founder time; must allow easy human review and line-item adjustment before client receives PDF. | K9: $499 - $999 / month | L9: Proposify, PandaDoc, manual Google Docs | M9: High | N9: FastAPI backend, ReportLab PDF, OpenAI Structured Outputs, Slack | O9: $35 - $50 / month | P9: Cuts proposal preparation time from 12 hours to 30 minutes; doubles quote turnaround speed. | Q9: Solution Validated | R9: Implement PDF quotation tool with ReportLab and Jinja2 templates (PRJ-008).
A10: VAL-006 | B10: Automated Commercial Fleet & Freight Brokerage Assistant | C10: Logistics & Freight Brokerage | D10: Freight brokers & mid-size trucking fleet dispatchers | E10: Brokers spend hours answering carrier phone calls asking 'is this load still available?' and negotiating per-mile rates. | F10: Brokers manually answer phone calls and emails, check TMS database, and haggle rates within $0.20/mile buffer. | G10: $3,500/mo freight coordinator salary per seat; high turnover and stress. | H10: AI Dispatch Employee answering email & web freight inquiries, confirming truck capacity, negotiating rate within predefined buffer, and generating rate confirmations. | I10: 2027-09-08 | J10: High volume, but industry has legacy software; TMS integration via API or email parser is mandatory. | K10: $600 - $1,500 / month per dispatcher seat | L10: Truckstop.com, DAT loadboards, manual broker teams | M10: Medium | N10: Transportation Management System (TMS) API / Email webhooks, PDF parser | O10: $45 - $80 / month | P10: Allows a 5-broker office to handle double the freight volume without adding staff. | Q10: Problem Confirmed | R10: Identify open TMS API sandbox for logistics load query integration.
